4.m_sequence_8bit/m_sequence_8bit.v
module m_sequence_8bit (
    input wire clk,      // 时钟信号，驱动移位寄存器的移位操作
    input wire rst_n,    // 异步复位信号，低电平有效，用于初始化移位寄存器
    output m_seq     // 输出的 m 序列信号
);

    reg [7:0] shift_reg; // 定义一个 8 位的移位寄存器

    always @(posedge clk or negedge rst_n) begin
        if (!rst_n) begin
            shift_reg <= 8'b00000001; // 异步复位，将移位寄存器初始化为非零状态，这里选择 00000001
        end else begin
            // 根据本原多项式 x^8 + x^4 + x^3 + x^2 + 1 进行反馈操作
            shift_reg[7:1] <= shift_reg[6:0]; // 移位操作，将低 7 位依次移到高 7 位
            shift_reg[0] <= shift_reg[7] ^ shift_reg[4] ^ shift_reg[3] ^ shift_reg[2]; // 异或反馈
        end
    end

    assign m_seq = shift_reg[7]; // 取移位寄存器的最高位作为 m 序列的输出

endmodule

04. m_sequence_8bit/m_sequence_8bit_tb.v
`timescale 1ns / 1ps

module m_sequence_tb;

    // 输入信号
    reg clk;
    reg rst_n;

    // 输出信号
    wire m_seq;

    // 实例化 m_sequence_8bit 模块
    m_sequence_8bit uut (
        .clk(clk),
        .rst_n(rst_n),
        .m_seq(m_seq)
    );

    // 时钟生成
    initial begin
        clk = 0;
        forever #5 clk = ~clk; // 10ns 周期，即 100MHz 时钟
    end

    // 测试过程
    initial begin
    // 初始化
        rst_n = 0;
        $dumpfile("m_sequence_8bit_tb.vcd");
        $dumpvars(0, m_sequence_tb);
        #10;
        rst_n = 1;
        #1000;

        // 结束仿真
        $finish;
    end

    // 监视输出
    initial begin
        $monitor("At time %t, m_seq = %b", $time, m_seq);
    end

endmodule

04. m_sequence_8bit/m_sequence_8bit_tb.vcd
$date
	Wed Feb 18 21:26:33 2026
$end
$version
	Icarus Verilog
$end
$timescale
	1ps
$end
$scope module m_sequence_tb $end
$var wire 1 ! m_seq $end
$var reg 1 " clk $end
$var reg 1 # rst_n $end
$scope module uut $end
$var wire 1 " clk $end
$var wire 1 # rst_n $end
$var wire 1 ! m_seq $end
$var reg 8 $ shift_reg [7:0] $end
$upscope $end
$upscope $end
$enddefinitions $end
#0
$dumpvars
b1 $
0#
0"
0!
$end
#5000
1"
#10000
0"
1#
#15000
b10 $
1"
#20000
0"
#25000
b100 $
1"
#30000
0"
#35000
b1001 $
1"
#40000
0"
#45000
b10011 $
1"
#50000
0"
#55000
b100111 $
1"
#60000
0"
#65000
b1001111 $
1"
#70000
0"
#75000
1!
b10011110 $
1"
#80000
0"
#85000
0!
b111100 $
1"
#90000
0"
#95000
b1111001 $
1"
#100000
0"
#105000
1!
b11110010 $
1"
#110000
0"
#115000
b11100100 $
1"
#120000
0"
#125000
b11001000 $
1"
#130000
0"
#135000
b10010000 $
1"
#140000
0"
#145000
0!
b100000 $
1"
#150000
0"
#155000
b1000000 $
1"
#160000
0"
#165000
1!
b10000000 $
1"
#170000
0"
#175000
0!
b1 $
1"
#180000
0"
#185000
b10 $
1"
#190000
0"
#195000
b100 $
1"
#200000
0"
#205000
b1001 $
1"
#210000
0"
#215000
b10011 $
1"
#220000
0"
#225000
b100111 $
1"
#230000
0"
#235000
b1001111 $
1"
#240000
0"
#245000
1!
b10011110 $
1"
#250000
0"
#255000
0!
b111100 $
1"
#260000
0"
#265000
b1111001 $
1"
#270000
0"
#275000
1!
b11110010 $
1"
#280000
0"
#285000
b11100100 $
1"
#290000
0"
#295000
b11001000 $
1"
#300000
0"
#305000
b10010000 $
1"
#310000
0"
#315000
0!
b100000 $
1"
#320000
0"
#325000
b1000000 $
1"
#330000
0"
#335000
1!
b10000000 $
1"
#340000
0"
#345000
0!
b1 $
1"
#350000
0"
#355000
b10 $
1"
#360000
0"
#365000
b100 $
1"
#370000
0"
#375000
b1001 $
1"
#380000
0"
#385000
b10011 $
1"
#390000
0"
#395000
b100111 $
1"
#400000
0"
#405000
b1001111 $
1"
#410000
0"
#415000
1!
b10011110 $
1"
#420000
0"
#425000
0!
b111100 $
1"
#430000
0"
#435000
b1111001 $
1"
#440000
0"
#445000
1!
b11110010 $
1"
#450000
0"
#455000
b11100100 $
1"
#460000
0"
#465000
b11001000 $
1"
#470000
0"
#475000
b10010000 $
1"
#480000
0"
#485000
0!
b100000 $
1"
#490000
0"
#495000
b1000000 $
1"
#500000
0"
#505000
1!
b10000000 $
1"
#510000
0"
#515000
0!
b1 $
1"
#520000
0"
#525000
b10 $
1"
#530000
0"
#535000
b100 $
1"
#540000
0"
#545000
b1001 $
1"
#550000
0"
#555000
b10011 $
1"
#560000
0"
#565000
b100111 $
1"
#570000
0"
#575000
b1001111 $
1"
#580000
0"
#585000
1!
b10011110 $
1"
#590000
0"
#595000
0!
b111100 $
1"
#600000
0"
#605000
b1111001 $
1"
#610000
0"
#615000
1!
b11110010 $
1"
#620000
0"
#625000
b11100100 $
1"
#630000
0"
#635000
b11001000 $
1"
#640000
0"
#645000
b10010000 $
1"
#650000
0"
#655000
0!
b100000 $
1"
#660000
0"
#665000
b1000000 $
1"
#670000
0"
#675000
1!
b10000000 $
1"
#680000
0"
#685000
0!
b1 $
1"
#690000
0"
#695000
b10 $
1"
#700000
0"
#705000
b100 $
1"
#710000
0"
#715000
b1001 $
1"
#720000
0"
#725000
b10011 $
1"
#730000
0"
#735000
b100111 $
1"
#740000
0"
#745000
b1001111 $
1"
#750000
0"
#755000
1!
b10011110 $
1"
#760000
0"
#765000
0!
b111100 $
1"
#770000
0"
#775000
b1111001 $
1"
#780000
0"
#785000
1!
b11110010 $
1"
#790000
0"
#795000
b11100100 $
1"
#800000
0"
#805000
b11001000 $
1"
#810000
0"
#815000
b10010000 $
1"
#820000
0"
#825000
0!
b100000 $
1"
#830000
0"
#835000
b1000000 $
1"
#840000
0"
#845000
1!
b10000000 $
1"
#850000
0"
#855000
0!
b1 $
1"
#860000
0"
#865000
b10 $
1"
#870000
0"
#875000
b100 $
1"
#880000
0"
#885000
b1001 $
1"
#890000
0"
#895000
b10011 $
1"
#900000
0"
#905000
b100111 $
1"
#910000
0"
#915000
b1001111 $
1"
#920000
0"
#925000
1!
b10011110 $
1"
#930000
0"
#935000
0!
b111100 $
1"
#940000
0"
#945000
b1111001 $
1"
#950000
0"
#955000
1!
b11110010 $
1"
#960000
0"
#965000
b11100100 $
1"
#970000
0"
#975000
b11001000 $
1"
#980000
0"
#985000
b10010000 $
1"
#990000
0"
#995000
0!
b100000 $
1"
#1000000
0"
#1005000
b1000000 $
1"
