15. dds/dds.v
module dds(
    input clk, //48khz
    input rst_n,
    input [9:0]dds_freq, //48hz/div
    output reg signed [15:0]ddso
  );

  reg signed [15:0]sin_rom[0:1023];

  integer i;

  initial
  begin
    for(i=0;i<1024;i=i+1)
    begin
      sin_rom[i] = 32700 * $sin(2*3.14159*i/1024);
    end
  end

  reg [9:0]addr;

  always@(posedge clk or negedge rst_n)
  begin
    if(!rst_n)
    begin
      addr <= 0;
      ddso <= 0;
    end
    else
    begin
      addr <= addr + dds_freq;
      ddso <= sin_rom[addr];
    end
  end

endmodule

15. dds/dds_tb.v
`timescale 1ns / 1ps
// 模块: dds_tb
// 说明: 验证 DDS 正弦波发生器
//       - 验证复位后输出为0
//       - 验证频率字为1时输出连续采样，不出现 X/Z
//       - 输出 VCD 波形供肉眼验证正弦形状

module dds_tb;

  reg         clk;
  reg         rst_n;
  reg  [9:0]  dds_freq;
  wire signed [15:0] ddso;

  dds dut (
    .clk     (clk),
    .rst_n   (rst_n),
    .dds_freq(dds_freq),
    .ddso    (ddso)
  );

  always #10 clk = ~clk;   // 50MHz（实际DDS用48kHz，这里仿真加速）

  integer err = 0;
  integer i;
  reg signed [15:0] samples [0:1023];

  initial begin
    $dumpfile("dds_tb.vcd");
    $dumpvars(0, dds_tb);

    clk      = 0;
    rst_n    = 0;
    dds_freq = 10'd0;

    // ── 复位验证 ──────────────────────────────────────
    repeat(3) @(posedge clk);
    rst_n = 1;
    @(posedge clk); #1;

    // ── 场景1：freq=0，输出应保持 sin_rom[0]=0 附近 ──
    dds_freq = 10'd0;
    repeat(5) @(posedge clk);
    if (ddso === 16'bx || ddso === 16'bz) begin
      $display("[FAIL] freq=0 时 ddso 为 X/Z");
      err = err + 1;
    end else
      $display("[PASS] freq=0, ddso=%0d (期望≈0)", ddso);

    // ── 场景2：freq=1，采集1024个样本，验证无X/Z ─────
    dds_freq = 10'd1;
    for (i = 0; i < 1024; i = i + 1) begin
      @(posedge clk); #1;
      samples[i] = ddso;
      if (ddso === 16'bx || ddso === 16'bz) begin
        $display("[FAIL] freq=1 第%0d个样本为 X/Z", i);
        err = err + 1;
      end
    end
    if (err == 0)
      $display("[PASS] freq=1，1024个样本均有效，最大值=%0d 最小值=%0d",
               samples[256], samples[768]);  // 正弦波峰/谷位置

    // ── 场景3：freq=4，验证正值出现 ───────────────────
    dds_freq = 10'd4;
    repeat(100) @(posedge clk);
    $display("[INFO] freq=4, ddso=%0d", ddso);

    // ── 场景4：复位后恢复到0 ──────────────────────────
    rst_n = 0;
    @(posedge clk); #1;
    if (ddso !== 16'sd0) begin
      $display("[FAIL] 复位后 ddso=%0d (期望0)", ddso);
      err = err + 1;
    end else
      $display("[PASS] 复位有效，ddso=0");
    rst_n = 1;

    repeat(5) @(posedge clk);

    if (err == 0)
      $display("[RESULT] dds 全部测试通过");
    else
      $display("[RESULT] dds 存在 %0d 个错误", err);

    $finish;
  end

  initial begin
    #2_000_000;
    $display("[TIMEOUT] dds 仿真超时");
    $finish;
  end
endmodule

15. dds/dds_tb.vcd
$date
	Wed Feb 18 21:31:58 2026
$end
$version
	Icarus Verilog
$end
$timescale
	1ps
$end
$scope module dds_tb $end
$var wire 16 ! ddso [15:0] $end
$var reg 1 " clk $end
$var reg 10 # dds_freq [9:0] $end
$var reg 1 $ rst_n $end
$var integer 32 % err [31:0] $end
$var integer 32 & i [31:0] $end
$scope module dut $end
$var wire 1 " clk $end
$var wire 10 ' dds_freq [9:0] $end
$var wire 1 $ rst_n $end
$var reg 10 ( addr [9:0] $end
$var reg 16 ) ddso [15:0] $end
$var integer 32 * i [31:0] $end
$upscope $end
$upscope $end
$enddefinitions $end
#0
$dumpvars
b10000000000 *
b0 )
b0 (
b0 '
bx &
b0 %
0$
b0 #
0"
b0 !
$end
#10000
1"
#20000
0"
#30000
1"
#40000
0"
#50000
1$
1"
#60000
0"
#70000
1"
#80000
0"
#90000
1"
#100000
0"
#110000
1"
#120000
0"
#130000
1"
#140000
0"
#150000
1"
#160000
0"
#170000
b1 (
b0 &
b1 #
b1 '
1"
#180000
0"
#190000
b11001001 !
b11001001 )
b10 (
1"
#191000
b1 &
#200000
0"
#210000
b110010001 !
b110010001 )
b11 (
1"
#211000
b10 &
#220000
0"
#230000
b1001011010 !
b1001011010 )
b100 (
1"
#231000
b11 &
#240000
0"
#250000
b1100100010 !
b1100100010 )
b101 (
1"
#251000
b100 &
#260000
0"
#270000
b1111101011 !
b1111101011 )
b110 (
1"
#271000
b101 &
#280000
0"
#290000
b10010110100 !
b10010110100 )
b111 (
1"
#291000
b110 &
#300000
0"
#310000
b10101111100 !
b10101111100 )
b1000 (
1"
#311000
b111 &
#320000
0"
#330000
b11001000101 !
b11001000101 )
b1001 (
1"
#331000
b1000 &
#340000
0"
#350000
b11100001101 !
b11100001101 )
b1010 (
1"
#351000
b1001 &
#360000
0"
#370000
b11111010101 !
b11111010101 )
b1011 (
1"
#371000
b1010 &
#380000
0"
#390000
b100010011101 !
b100010011101 )
b1100 (
1"
#391000
b1011 &
#400000
0"
#410000
b100101100110 !
b100101100110 )
b1101 (
1"
#411000
b1100 &
#420000
0"
#430000
b101000101110 !
b101000101110 )
b1110 (
1"
#431000
b1101 &
#440000
0"
#450000
b101011110110 !
b101011110110 )
b1111 (
1"
#451000
b1110 &
#460000
0"
#470000
b101110111101 !
b101110111101 )
b10000 (
1"
#471000
b1111 &
#480000
0"
#490000
b110010000101 !
b110010000101 )
b10001 (
1"
#491000
b10000 &
#500000
0"
#510000
b110101001101 !
b110101001101 )
b10010 (
1"
#511000
b10001 &
#520000
0"
#530000
b111000010100 !
b111000010100 )
b10011 (
1"
#531000
b10010 &
#540000
0"
#550000
b111011011100 !
b111011011100 )
b10100 (
1"
#551000
b10011 &
#560000
0"
#570000
b111110100011 !
b111110100011 )
b10101 (
1"
#571000
b10100 &
#580000
0"
#590000
b1000001101010 !
b1000001101010 )
b10110 (
1"
#591000
b10101 &
#600000
0"
#610000
b1000100110001 !
b1000100110001 )
b10111 (
1"
#611000
b10110 &
#620000
0"
#630000
b1000111111000 !
b1000111111000 )
b11000 (
1"
#631000
b10111 &
#640000
0"
#650000
b1001010111110 !
b1001010111110 )
b11001 (
1"
#651000
b11000 &
#660000
0"
#670000
b1001110000100 !
b1001110000100 )
b11010 (
1"
#671000
b11001 &
#680000
0"
#690000
b1010001001011 !
b1010001001011 )
b11011 (
1"
#691000
b11010 &
#700000
0"
#710000
b1010100010001 !
b1010100010001 )
b11100 (
1"
#711000
b11011 &
#720000
0"
#730000
b1010111010110 !
b1010111010110 )
b11101 (
1"
#731000
b11100 &
#740000
0"
#750000
b1011010011100 !
b1011010011100 )
b11110 (
1"
#751000
b11101 &
#760000
0"
#770000
b1011101100001 !
b1011101100001 )
b11111 (
1"
#771000
b11110 &
#780000
0"
#790000
b1100000100111 !
b1100000100111 )
b100000 (
1"
#791000
b11111 &
#800000
0"
#810000
b1100011101011 !
b1100011101011 )
b100001 (
1"
#811000
b100000 &
#820000
0"
#830000
b1100110110000 !
b1100110110000 )
b100010 (
1"
#831000
b100001 &
#840000
0"
#850000
b1101001110101 !
b1101001110101 )
b100011 (
1"
#851000
b100010 &
#860000
0"
#870000
b1101100111001 !
b1101100111001 )
b100100 (
1"
#871000
b100011 &
#880000
0"
#890000
b1101111111101 !
b1101111111101 )
b100101 (
1"
#891000
b100100 &
#900000
0"
#910000
b1110011000000 !
b1110011000000 )
b100110 (
1"
#911000
b100101 &
#920000
0"
#930000
b1110110000100 !
b1110110000100 )
b100111 (
1"
#931000
b100110 &
#940000
0"
#950000
b1111001000111 !
b1111001000111 )
b101000 (
1"
#951000
b100111 &
#960000
0"
#970000
b1111100001001 !
b1111100001001 )
b101001 (
1"
#971000
b101000 &
#980000
0"
#990000
b1111111001100 !
b1111111001100 )
b101010 (
1"
#991000
b101001 &
#1000000
0"
#1010000
b10000010001110 !
b10000010001110 )
b101011 (
1"
#1011000
b101010 &
#1020000
0"
#1030000
b10000101010000 !
b10000101010000 )
b101100 (
1"
#1031000
b101011 &
#1040000
0"
#1050000
b10001000010001 !
b10001000010001 )
b101101 (
1"
#1051000
b101100 &
#1060000
0"
#1070000
b10001011010011 !
b10001011010011 )
b101110 (
1"
#1071000
b101101 &
#1080000
0"
#1090000
b10001110010100 !
b10001110010100 )
b101111 (
1"
#1091000
b101110 &
#1100000
0"
#1110000
b10010001010100 !
b10010001010100 )
b110000 (
1"
#1111000
b101111 &
#1120000
0"
#1130000
b10010100010100 !
b10010100010100 )
b110001 (
1"
#1131000
b110000 &
#1140000
0"
#1150000
b10010111010100 !
b10010111010100 )
b110010 (
1"
#1151000
b110001 &
#1160000
0"
#1170000
b10011010010100 !
b10011010010100 )
b110011 (
1"
#1171000
b110010 &
#1180000
0"
#1190000
b10011101010011 !
b10011101010011 )
b110100 (
1"
#1191000
b110011 &
#1200000
0"
#1210000
b10100000010001 !
b10100000010001 )
b110101 (
1"
#1211000
b110100 &
#1220000
0"
#1230000
b10100011010000 !
b10100011010000 )
b110110 (
1"
#1231000
b110101 &
#1240000
0"
#1250000
b10100110001110 !
b10100110001110 )
b110111 (
1"
#1251000
b110110 &
#1260000
0"
#1270000
b10101001001011 !
b10101001001011 )
b111000 (
1"
#1271000
b110111 &
#1280000
0"
#1290000
b10101100001000 !
b10101100001000 )
b111001 (
1"
#1291000
b111000 &
#1300000
0"
#1310000
b10101111000101 !
b10101111000101 )
b111010 (
1"
#1311000
b111001 &
#1320000
0"
#1330000
b10110010000001 !
b10110010000001 )
b111011 (
1"
#1331000
b111010 &
#1340000
0"
#1350000
b10110100111101 !
b10110100111101 )
b111100 (
1"
#1351000
b111011 &
#1360000
0"
#1370000
b10110111111001 !
b10110111111001 )
b111101 (
1"
#1371000
b111100 &
#1380000
0"
#1390000
b10111010110100 !
b10111010110100 )
b111110 (
1"
#1391000
b111101 &
#1400000
0"
#1410000
b10111101101110 !
b10111101101110 )
b111111 (
1"
#1411000
b111110 &
#1420000
0"
#1430000
b11000000101000 !
b11000000101000 )
b1000000 (
1"
#1431000
b111111 &
#1440000
0"
#1450000
b11000011100010 !
b11000011100010 )
b1000001 (
1"
#1451000
b1000000 &
#1460000
0"
#1470000
b11000110011011 !
b11000110011011 )
b1000010 (
1"
#1471000
b1000001 &
#1480000
0"
#1490000
b11001001010100 !
b11001001010100 )
b1000011 (
1"
#1491000
b1000010 &
#1500000
0"
#1510000
b11001100001100 !
b11001100001100 )
b1000100 (
1"
#1511000
b1000011 &
#1520000
0"
#1530000
b11001111000011 !
b11001111000011 )
b1000101 (
1"
#1531000
b1000100 &
#1540000
0"
#1550000
b11010001111011 !
b11010001111011 )
b1000110 (
1"
#1551000
b1000101 &
#1560000
0"
#1570000
b11010100110001 !
b11010100110001 )
b1000111 (
1"
#1571000
b1000110 &
#1580000
0"
#1590000
b11010111100111 !
b11010111100111 )
b1001000 (
1"
#1591000
b1000111 &
#1600000
0"
#1610000
b11011010011101 !
b11011010011101 )
b1001001 (
1"
#1611000
b1001000 &
#1620000
0"
#1630000
b11011101010010 !
b11011101010010 )
b1001010 (
1"
#1631000
b1001001 &
#1640000
0"
#1650000
b11100000000111 !
b11100000000111 )
b1001011 (
1"
#1651000
b1001010 &
#1660000
0"
#1670000
b11100010111011 !
b11100010111011 )
b1001100 (
1"
#1671000
b1001011 &
#1680000
0"
#1690000
b11100101101110 !
b11100101101110 )
b1001101 (
1"
#1691000
b1001100 &
#1700000
0"
#1710000
b11101000100001 !
b11101000100001 )
b1001110 (
1"
#1711000
b1001101 &
#1720000
0"
#1730000
b11101011010100 !
b11101011010100 )
b1001111 (
1"
#1731000
b1001110 &
#1740000
0"
#1750000
b11101110000101 !
b11101110000101 )
b1010000 (
1"
#1751000
b1001111 &
#1760000
0"
#1770000
b11110000110111 !
b11110000110111 )
b1010001 (
1"
#1771000
b1010000 &
#1780000
0"
#1790000
b11110011100111 !
b11110011100111 )
b1010010 (
1"
#1791000
b1010001 &
#1800000
0"
#1810000
b11110110010111 !
b11110110010111 )
b1010011 (
1"
#1811000
b1010010 &
#1820000
0"
#1830000
b11111001000111 !
b11111001000111 )
b1010100 (
1"
#1831000
b1010011 &
#1840000
0"
#1850000
b11111011110110 !
b11111011110110 )
b1010101 (
1"
#1851000
b1010100 &
#1860000
0"
#1870000
b11111110100100 !
b11111110100100 )
b1010110 (
1"
#1871000
b1010101 &
#1880000
0"
#1890000
b100000001010010 !
b100000001010010 )
b1010111 (
1"
#1891000
b1010110 &
#1900000
0"
#1910000
b100000011111111 !
b100000011111111 )
b1011000 (
1"
#1911000
b1010111 &
#1920000
0"
#1930000
b100000110101011 !
b100000110101011 )
b1011001 (
1"
#1931000
b1011000 &
#1940000
0"
#1950000
b100001001010111 !
b100001001010111 )
b1011010 (
1"
#1951000
b1011001 &
#1960000
0"
#1970000
b100001100000010 !
b100001100000010 )
b1011011 (
1"
#1971000
b1011010 &
#1980000
0"
#1990000
b100001110101101 !
b100001110101101 )
b1011100 (
1"
#1991000
b1011011 &
#2000000
0"
#2010000
b100010001010110 !
b100010001010110 )
b1011101 (
1"
#2011000
b1011100 &
#2020000
0"
#2030000
b100010100000000 !
b100010100000000 )
b1011110 (
1"
#2031000
b1011101 &
#2040000
0"
#2050000
b100010110101000 !
b100010110101000 )
b1011111 (
1"
#2051000
b1011110 &
#2060000
0"
#2070000
b100011001010000 !
b100011001010000 )
b1100000 (
1"
#2071000
b1011111 &
#2080000
0"
#2090000
b100011011110111 !
b100011011110111 )
b1100001 (
1"
#2091000
b1100000 &
#2100000
0"
#2110000
b100011110011110 !
b100011110011110 )
b1100010 (
1"
#2111000
b1100001 &
#2120000
0"
#2130000
b100100001000011 !
b100100001000011 )
b1100011 (
1"
#2131000
b1100010 &
#2140000
0"
#2150000
b100100011101001 !
b100100011101001 )
b1100100 (
1"
#2151000
b1100011 &
#2160000
0"
#2170000
b100100110001101 !
b100100110001101 )
b1100101 (
1"
#2171000
b1100100 &
#2180000
0"
#2190000
b100101000110001 !
b100101000110001 )
b1100110 (
1"
#2191000
b1100101 &
#2200000
0"
#2210000
b100101011010100 !
b100101011010100 )
b1100111 (
1"
#2211000
b1100110 &
#2220000
0"
#2230000
b100101101110110 !
b100101101110110 )
b1101000 (
1"
#2231000
b1100111 &
#2240000
0"
#2250000
b100110000010111 !
b100110000010111 )
b1101001 (
1"
#2251000
b1101000 &
#2260000
0"
#2270000
b100110010111000 !
b100110010111000 )
b1101010 (
1"
#2271000
b1101001 &
#2280000
0"
#2290000
b100110101011000 !
b100110101011000 )
b1101011 (
1"
#2291000
b1101010 &
#2300000
0"
#2310000
b100110111111000 !
b100110111111000 )
b1101100 (
1"
#2311000
b1101011 &
#2320000
0"
#2330000
b100111010010110 !
b100111010010110 )
b1101101 (
1"
#2331000
b1101100 &
#2340000
0"
#2350000
b100111100110100 !
b100111100110100 )
b1101110 (
1"
#2351000
b1101101 &
#2360000
0"
#2370000
b100111111010001 !
b100111111010001 )
b1101111 (
1"
#2371000
b1101110 &
#2380000
0"
#2390000
b101000001101101 !
b101000001101101 )
b1110000 (
1"
#2391000
b1101111 &
#2400000
0"
#2410000
b101000100001001 !
b101000100001001 )
b1110001 (
1"
#2411000
b1110000 &
#2420000
0"
#2430000
b101000110100011 !
b101000110100011 )
b1110010 (
1"
#2431000
b1110001 &
#2440000
0"
#2450000
b101001000111101 !
b101001000111101 )
b1110011 (
1"
#2451000
b1110010 &
#2460000
0"
#2470000
b101001011010110 !
b101001011010110 )
b1110100 (
1"
#2471000
b1110011 &
#2480000
0"
#2490000
b101001101101111 !
b101001101101111 )
b1110101 (
1"
#2491000
b1110100 &
#2500000
0"
#2510000
b101010000000110 !
b101010000000110 )
b1110110 (
1"
#2511000
b1110101 &
#2520000
0"
#2530000
b101010010011101 !
b101010010011101 )
b1110111 (
1"
#2531000
b1110110 &
#2540000
0"
#2550000
b101010100110011 !
b101010100110011 )
b1111000 (
1"
#2551000
b1110111 &
#2560000
0"
#2570000
b101010111001000 !
b101010111001000 )
b1111001 (
1"
#2571000
b1111000 &
#2580000
0"
#2590000
b101011001011100 !
b101011001011100 )
b1111010 (
1"
#2591000
b1111001 &
#2600000
0"
#2610000
b101011011110000 !
b101011011110000 )
b1111011 (
1"
#2611000
b1111010 &
#2620000
0"
#2630000
b101011110000010 !
b101011110000010 )
b1111100 (
1"
#2631000
b1111011 &
#2640000
0"
#2650000
b101100000010100 !
b101100000010100 )
b1111101 (
1"
#2651000
b1111100 &
#2660000
0"
#2670000
b101100010100101 !
b101100010100101 )
b1111110 (
1"
#2671000
b1111101 &
#2680000
0"
#2690000
b101100100110101 !
b101100100110101 )
b1111111 (
1"
#2691000
b1111110 &
#2700000
0"
#2710000
b101100111000100 !
b101100111000100 )
b10000000 (
1"
#2711000
b1111111 &
#2720000
0"
#2730000
b101101001010010 !
b101101001010010 )
b10000001 (
1"
#2731000
b10000000 &
#2740000
0"
#2750000
b101101011100000 !
b101101011100000 )
b10000010 (
1"
#2751000
b10000001 &
#2760000
0"
#2770000
b101101101101100 !
b101101101101100 )
b10000011 (
1"
#2771000
b10000010 &
#2780000
0"
#2790000
b101101111111000 !
b101101111111000 )
b10000100 (
1"
#2791000
b10000011 &
#2800000
0"
#2810000
b101110010000011 !
b101110010000011 )
b10000101 (
1"
#2811000
b10000100 &
#2820000
0"
#2830000
b101110100001101 !
b101110100001101 )
b10000110 (
1"
#2831000
b10000101 &
#2840000
0"
#2850000
b101110110010110 !
b101110110010110 )
b10000111 (
1"
#2851000
b10000110 &
#2860000
0"
#2870000
b101111000011110 !
b101111000011110 )
b10001000 (
1"
#2871000
b10000111 &
#2880000
0"
#2890000
b101111010100101 !
b101111010100101 )
b10001001 (
1"
#2891000
b10001000 &
#2900000
0"
#2910000
b101111100101011 !
b101111100101011 )
b10001010 (
1"
#2911000
b10001001 &
#2920000
0"
#2930000
b101111110110001 !
b101111110110001 )
b10001011 (
1"
#2931000
b10001010 &
#2940000
0"
#2950000
b110000000110101 !
b110000000110101 )
b10001100 (
1"
#2951000
b10001011 &
#2960000
0"
#2970000
b110000010111001 !
b110000010111001 )
b10001101 (
1"
#2971000
b10001100 &
#2980000
0"
#2990000
b110000100111011 !
b110000100111011 )
b10001110 (
1"
#2991000
b10001101 &
#3000000
0"
#3010000
b110000110111101 !
b110000110111101 )
b10001111 (
1"
#3011000
b10001110 &
#3020000
0"
#3030000
b110001000111110 !
b110001000111110 )
b10010000 (
1"
#3031000
b10001111 &
#3040000
0"
#3050000
b110001010111101 !
b110001010111101 )
b10010001 (
1"
#3051000
b10010000 &
#3060000
0"
#3070000
b110001100111100 !
b110001100111100 )
b10010010 (
1"
#3071000
b10010001 &
#3080000
0"
#3090000
b110001110111010 !
b110001110111010 )
b10010011 (
1"
#3091000
b10010010 &
#3100000
0"
#3110000
b110010000110111 !
b110010000110111 )
b10010100 (
1"
#3111000
b10010011 &
#3120000
0"
#3130000
b110010010110011 !
b110010010110011 )
b10010101 (
1"
#3131000
b10010100 &
#3140000
0"
#3150000
b110010100101110 !
b110010100101110 )
b10010110 (
1"
#3151000
b10010101 &
#3160000
0"
#3170000
b110010110101000 !
b110010110101000 )
b10010111 (
1"
#3171000
b10010110 &
#3180000
0"
#3190000
b110011000100001 !
b110011000100001 )
b10011000 (
1"
#3191000
b10010111 &
#3200000
0"
#3210000
b110011010011001 !
b110011010011001 )
b10011001 (
1"
#3211000
b10011000 &
#3220000
0"
#3230000
b110011100010000 !
b110011100010000 )
b10011010 (
1"
#3231000
b10011001 &
#3240000
0"
#3250000
b110011110000110 !
b110011110000110 )
b10011011 (
1"
#3251000
b10011010 &
#3260000
0"
#3270000
b110011111111011 !
b110011111111011 )
b10011100 (
1"
#3271000
b10011011 &
#3280000
0"
#3290000
b110100001101111 !
b110100001101111 )
b10011101 (
1"
#3291000
b10011100 &
#3300000
0"
#3310000
b110100011100010 !
b110100011100010 )
b10011110 (
1"
#3311000
b10011101 &
#3320000
0"
#3330000
b110100101010100 !
b110100101010100 )
b10011111 (
1"
#3331000
b10011110 &
#3340000
0"
#3350000
b110100111000101 !
b110100111000101 )
b10100000 (
1"
#3351000
b10011111 &
#3360000
0"
#3370000
b110101000110101 !
b110101000110101 )
b10100001 (
1"
#3371000
b10100000 &
#3380000
0"
#3390000
b110101010100100 !
b110101010100100 )
b10100010 (
1"
#3391000
b10100001 &
#3400000
0"
#3410000
b110101100010010 !
b110101100010010 )
b10100011 (
1"
#3411000
b10100010 &
#3420000
0"
#3430000
b110101101111111 !
b110101101111111 )
b10100100 (
1"
#3431000
b10100011 &
#3440000
0"
#3450000
b110101111101011 !
b110101111101011 )
b10100101 (
1"
#3451000
b10100100 &
#3460000
0"
#3470000
b110110001010110 !
b110110001010110 )
b10100110 (
1"
#3471000
b10100101 &
#3480000
0"
#3490000
b110110010111111 !
b110110010111111 )
b10100111 (
1"
#3491000
b10100110 &
#3500000
0"
#3510000
b110110100101000 !
b110110100101000 )
b10101000 (
1"
#3511000
b10100111 &
#3520000
0"
#3530000
b110110110010000 !
b110110110010000 )
b10101001 (
1"
#3531000
b10101000 &
#3540000
0"
#3550000
b110110111110110 !
b110110111110110 )
b10101010 (
1"
#3551000
b10101001 &
#3560000
0"
#3570000
b110111001011100 !
b110111001011100 )
b10101011 (
1"
#3571000
b10101010 &
#3580000
0"
#3590000
b110111011000000 !
b110111011000000 )
b10101100 (
1"
#3591000
b10101011 &
#3600000
0"
#3610000
b110111100100100 !
b110111100100100 )
b10101101 (
1"
#3611000
b10101100 &
#3620000
0"
#3630000
b110111110000110 !
b110111110000110 )
b10101110 (
1"
#3631000
b10101101 &
#3640000
0"
#3650000
b110111111100111 !
b110111111100111 )
b10101111 (
1"
#3651000
b10101110 &
#3660000
0"
#3670000
b111000001001000 !
b111000001001000 )
b10110000 (
1"
#3671000
b10101111 &
#3680000
0"
#3690000
b111000010100111 !
b111000010100111 )
b10110001 (
1"
#3691000
b10110000 &
#3700000
0"
#3710000
b111000100000101 !
b111000100000101 )
b10110010 (
1"
#3711000
b10110001 &
#3720000
0"
#3730000
b111000101100010 !
b111000101100010 )
b10110011 (
1"
#3731000
b10110010 &
#3740000
0"
#3750000
b111000110111110 !
b111000110111110 )
b10110100 (
1"
#3751000
b10110011 &
#3760000
0"
#3770000
b111001000011000 !
b111001000011000 )
b10110101 (
1"
#3771000
b10110100 &
#3780000
0"
#3790000
b111001001110010 !
b111001001110010 )
b10110110 (
1"
#3791000
b10110101 &
#3800000
0"
#3810000
b111001011001011 !
b111001011001011 )
b10110111 (
1"
#3811000
b10110110 &
#3820000
0"
#3830000
b111001100100010 !
b111001100100010 )
b10111000 (
1"
#3831000
b10110111 &
#3840000
0"
#3850000
b111001101111000 !
b111001101111000 )
b10111001 (
1"
#3851000
b10111000 &
#3860000
0"
#3870000
b111001111001110 !
b111001111001110 )
b10111010 (
1"
#3871000
b10111001 &
#3880000
0"
#3890000
b111010000100010 !
b111010000100010 )
b10111011 (
1"
#3891000
b10111010 &
#3900000
0"
#3910000
b111010001110101 !
b111010001110101 )
b10111100 (
1"
#3911000
b10111011 &
#3920000
0"
#3930000
b111010011000111 !
b111010011000111 )
b10111101 (
1"
#3931000
b10111100 &
#3940000
0"
#3950000
b111010100010111 !
b111010100010111 )
b10111110 (
1"
#3951000
b10111101 &
#3960000
0"
#3970000
b111010101100111 !
b111010101100111 )
b10111111 (
1"
#3971000
b10111110 &
#3980000
0"
#3990000
b111010110110101 !
b111010110110101 )
b11000000 (
1"
#3991000
b10111111 &
#4000000
0"
#4010000
b111011000000011 !
b111011000000011 )
b11000001 (
1"
#4011000
b11000000 &
#4020000
0"
#4030000
b111011001001111 !
b111011001001111 )
b11000010 (
1"
#4031000
b11000001 &
#4040000
0"
#4050000
b111011010011010 !
b111011010011010 )
b11000011 (
1"
#4051000
b11000010 &
#4060000
0"
#4070000
b111011011100100 !
b111011011100100 )
b11000100 (
1"
#4071000
b11000011 &
#4080000
0"
#4090000
b111011100101101 !
b111011100101101 )
b11000101 (
1"
#4091000
b11000100 &
#4100000
0"
#4110000
b111011101110100 !
b111011101110100 )
b11000110 (
1"
#4111000
b11000101 &
#4120000
0"
#4130000
b111011110111011 !
b111011110111011 )
b11000111 (
1"
#4131000
b11000110 &
#4140000
0"
#4150000
b111100000000000 !
b111100000000000 )
b11001000 (
1"
#4151000
b11000111 &
#4160000
0"
#4170000
b111100001000100 !
b111100001000100 )
b11001001 (
1"
#4171000
b11001000 &
#4180000
0"
#4190000
b111100010000111 !
b111100010000111 )
b11001010 (
1"
#4191000
b11001001 &
#4200000
0"
#4210000
b111100011001001 !
b111100011001001 )
b11001011 (
1"
#4211000
b11001010 &
#4220000
0"
#4230000
b111100100001010 !
b111100100001010 )
b11001100 (
1"
#4231000
b11001011 &
#4240000
0"
#4250000
b111100101001010 !
b111100101001010 )
b11001101 (
1"
#4251000
b11001100 &
#4260000
0"
#4270000
b111100110001000 !
b111100110001000 )
b11001110 (
1"
#4271000
b11001101 &
#4280000
0"
#4290000
b111100111000101 !
b111100111000101 )
b11001111 (
1"
#4291000
b11001110 &
#4300000
0"
#4310000
b111101000000001 !
b111101000000001 )
b11010000 (
1"
#4311000
b11001111 &
#4320000
0"
#4330000
b111101000111100 !
b111101000111100 )
b11010001 (
1"
#4331000
b11010000 &
#4340000
0"
#4350000
b111101001110110 !
b111101001110110 )
b11010010 (
1"
#4351000
b11010001 &
#4360000
0"
#4370000
b111101010101110 !
b111101010101110 )
b11010011 (
1"
#4371000
b11010010 &
#4380000
0"
#4390000
b111101011100101 !
b111101011100101 )
b11010100 (
1"
#4391000
b11010011 &
#4400000
0"
#4410000
b111101100011011 !
b111101100011011 )
b11010101 (
1"
#4411000
b11010100 &
#4420000
0"
#4430000
b111101101010000 !
b111101101010000 )
b11010110 (
1"
#4431000
b11010101 &
#4440000
0"
#4450000
b111101110000100 !
b111101110000100 )
b11010111 (
1"
#4451000
b11010110 &
#4460000
0"
#4470000
b111101110110111 !
b111101110110111 )
b11011000 (
1"
#4471000
b11010111 &
#4480000
0"
#4490000
b111101111101000 !
b111101111101000 )
b11011001 (
1"
#4491000
b11011000 &
#4500000
0"
#4510000
b111110000011000 !
b111110000011000 )
b11011010 (
1"
#4511000
b11011001 &
#4520000
0"
#4530000
b111110001000111 !
b111110001000111 )
b11011011 (
1"
#4531000
b11011010 &
#4540000
0"
#4550000
b111110001110101 !
b111110001110101 )
b11011100 (
1"
#4551000
b11011011 &
#4560000
0"
#4570000
b111110010100001 !
b111110010100001 )
b11011101 (
1"
#4571000
b11011100 &
#4580000
0"
#4590000
b111110011001101 !
b111110011001101 )
b11011110 (
1"
#4591000
b11011101 &
#4600000
0"
#4610000
b111110011110111 !
b111110011110111 )
b11011111 (
1"
#4611000
b11011110 &
#4620000
0"
#4630000
b111110100100000 !
b111110100100000 )
b11100000 (
1"
#4631000
b11011111 &
#4640000
0"
#4650000
b111110101001000 !
b111110101001000 )
b11100001 (
1"
#4651000
b11100000 &
#4660000
0"
#4670000
b111110101101110 !
b111110101101110 )
b11100010 (
1"
#4671000
b11100001 &
#4680000
0"
#4690000
b111110110010100 !
b111110110010100 )
b11100011 (
1"
#4691000
b11100010 &
#4700000
0"
#4710000
b111110110111000 !
b111110110111000 )
b11100100 (
1"
#4711000
b11100011 &
#4720000
0"
#4730000
b111110111011011 !
b111110111011011 )
b11100101 (
1"
#4731000
b11100100 &
#4740000
0"
#4750000
b111110111111100 !
b111110111111100 )
b11100110 (
1"
#4751000
b11100101 &
#4760000
0"
#4770000
b111111000011101 !
b111111000011101 )
b11100111 (
1"
#4771000
b11100110 &
#4780000
0"
#4790000
b111111000111100 !
b111111000111100 )
b11101000 (
1"
#4791000
b11100111 &
#4800000
0"
#4810000
b111111001011010 !
b111111001011010 )
b11101001 (
1"
#4811000
b11101000 &
#4820000
0"
#4830000
b111111001110111 !
b111111001110111 )
b11101010 (
1"
#4831000
b11101001 &
#4840000
0"
#4850000
b111111010010011 !
b111111010010011 )
b11101011 (
1"
#4851000
b11101010 &
#4860000
0"
#4870000
b111111010101101 !
b111111010101101 )
b11101100 (
1"
#4871000
b11101011 &
#4880000
0"
#4890000
b111111011000110 !
b111111011000110 )
b11101101 (
1"
#4891000
b11101100 &
#4900000
0"
#4910000
b111111011011110 !
b111111011011110 )
b11101110 (
1"
#4911000
b11101101 &
#4920000
0"
#4930000
b111111011110101 !
b111111011110101 )
b11101111 (
1"
#4931000
b11101110 &
#4940000
0"
#4950000
b111111100001010 !
b111111100001010 )
b11110000 (
1"
#4951000
b11101111 &
#4960000
0"
#4970000
b111111100011111 !
b111111100011111 )
b11110001 (
1"
#4971000
b11110000 &
#4980000
0"
#4990000
b111111100110010 !
b111111100110010 )
b11110010 (
1"
#4991000
b11110001 &
#5000000
0"
#5010000
b111111101000011 !
b111111101000011 )
b11110011 (
1"
#5011000
b11110010 &
#5020000
0"
#5030000
b111111101010100 !
b111111101010100 )
b11110100 (
1"
#5031000
b11110011 &
#5040000
0"
#5050000
b111111101100011 !
b111111101100011 )
b11110101 (
1"
#5051000
b11110100 &
#5060000
0"
#5070000
b111111101110010 !
b111111101110010 )
b11110110 (
1"
#5071000
b11110101 &
#5080000
0"
#5090000
b111111101111110 !
b111111101111110 )
b11110111 (
1"
#5091000
b11110110 &
#5100000
0"
#5110000
b111111110001010 !
b111111110001010 )
b11111000 (
1"
#5111000
b11110111 &
#5120000
0"
#5130000
b111111110010101 !
b111111110010101 )
b11111001 (
1"
#5131000
b11111000 &
#5140000
0"
#5150000
b111111110011110 !
b111111110011110 )
b11111010 (
1"
#5151000
b11111001 &
#5160000
0"
#5170000
b111111110100110 !
b111111110100110 )
b11111011 (
1"
