16. async_fifo/dpram.v
// 模块: dpram
// 说明: 双口 RAM（Dual-Port RAM）实现，用于 async_fifo 做底层存储。
// 主要参数:
//  - DATA_WIDTH: 数据宽度
//  - ADDR_WIDTH: 地址宽度（决定深度）
// 主要端口:
//  - wrclock/wren/wraddress/data: 写端口
//  - rdclock/rden/rdaddress/q: 读端口
// 说明/备注:
//  - 根据 ADDR_WIDTH 大小时选择 block RAM 或 distributed RAM 实现，使用合成属性提示。
// -----------------------------------------------------------------------------
module dpram #(
  parameter DATA_WIDTH = 16,
  parameter ADDR_WIDTH = 16
)
(
  input                    wrclock,
  input                    wren,
  input  [ADDR_WIDTH-1:0]  wraddress,
  input  [DATA_WIDTH-1:0]  data,
  input                    rdclock,
  input                    rden,
  input  [ADDR_WIDTH-1:0]  rdaddress,
  output [DATA_WIDTH-1:0]  q
);

reg [DATA_WIDTH-1:0] q_wire;

assign q = q_wire;

generate
  if(ADDR_WIDTH>5) begin : use_bram
  //
   (* ram_style = "block" *) reg [DATA_WIDTH-1:0] ram [2**ADDR_WIDTH-1:0];
  always@(posedge wrclock)
    if(wren)
      ram[wraddress] <= data;

  always@(posedge rdclock)
    if(rden)
      q_wire <= ram[rdaddress];
  //
  end
  else begin : use_dram
  //
  (* ram_style = "distributed" *) reg [DATA_WIDTH-1:0] ram [2**ADDR_WIDTH-1:0];
  always@(posedge wrclock)
    if(wren)
      ram[wraddress] <= data;

  always@(posedge rdclock)
    if(rden)
      q_wire <= ram[rdaddress];
  //
  end
endgenerate


endmodule

16. async_fifo/async_fifo_ctrl.v
`timescale 1ns / 1ps
// 模块: async_fifo_ctrl
// 说明: 异步 FIFO 控制器，负责写/读指针管理、灰码同步、空满标志计算以及写/读深度统计。
// 主要参数:
//  - DATA_WIDTH: 数据宽度
//  - ADDR_WIDTH: 地址宽度
//  - FULL_AHEAD: almost_full 阈值配置
// 主要端口:
//  - reset: 复位（高电平有效）
//  - wrclk/wren/wrdata: 写端接口
//  - rdclk/rden: 读端接口
//  - ram_dout/ram_wraddr/ram_rdaddr/ram_din/ram_wren: 与双口 RAM 的接口
// 说明/备注:
//  - 使用二进制-灰码互转进行跨时钟域指针同步，保证空满判定的可靠性。
// -----------------------------------------------------------------------------
module async_fifo_ctrl #(
  parameter DATA_WIDTH = 16,
  parameter ADDR_WIDTH = 16,
  parameter FULL_AHEAD = 1
)
(
  input                       reset,
  //fifo wr
  input                       wrclk,
  input                       wren,
  input      [DATA_WIDTH-1:0] wrdata,
  output reg                  full,
  output reg                  almost_full,
  output     [ADDR_WIDTH:0]   wrusedw,
  //fifo rd
  input                       rdclk,
  input                       rden,
  output     [DATA_WIDTH-1:0] rddata,
  output                      empty,
  output     [ADDR_WIDTH:0]   rdusedw,
  //ram
  input      [DATA_WIDTH-1:0] ram_dout,
  output     [ADDR_WIDTH-1:0] ram_wraddr,
  output     [ADDR_WIDTH-1:0] ram_rdaddr,
  output     [DATA_WIDTH-1:0] ram_din,
  output                      ram_wren
);

reg  [ADDR_WIDTH:0] wr_pntr;
wire [ADDR_WIDTH:0] wr_pntr_next;
wire [ADDR_WIDTH:0] wr_pntr_gray;
reg  [ADDR_WIDTH:0] wr_pntr_gray_reg;
reg  [ADDR_WIDTH:0] rdside_wr_pntr_gray;
reg  [ADDR_WIDTH:0] rdside_wr_pntr_gray_dly1;
wire [ADDR_WIDTH:0] rdside_wr_pntr_bin;

reg  [ADDR_WIDTH:0] rd_pntr;
wire [ADDR_WIDTH:0] rd_pntr_next;
wire [ADDR_WIDTH:0] rd_pntr_gray;
reg  [ADDR_WIDTH:0] rd_pntr_gray_reg;
reg  [ADDR_WIDTH:0] wrside_rd_pntr_gray;
reg  [ADDR_WIDTH:0] wrside_rd_pntr_gray_dly1;
wire [ADDR_WIDTH:0] wrside_rd_pntr_bin;

wire [ADDR_WIDTH:0] almost_full_threshold;

reg                 empty_pre;
reg                 empty_pre_dly1;

assign  rddata     = ram_dout;
assign  ram_din    = wrdata;
assign  ram_wren   = wren && !full;
assign  ram_wraddr = wr_pntr[ADDR_WIDTH-1:0];
assign  ram_rdaddr = rd_pntr_next[ADDR_WIDTH-1:0];

assign  almost_full_threshold = {1'b1,{ADDR_WIDTH{1'b0}}} - FULL_AHEAD[ADDR_WIDTH:0];

assign wr_pntr_next = wr_pntr + (~full & wren);
assign rd_pntr_next = rd_pntr + (~empty & rden);

always@(posedge wrclk or posedge reset)
  if(reset)
    wr_pntr <= 'd0;
  else
    wr_pntr <= wr_pntr_next;

always@(posedge rdclk or posedge reset)
  if(reset)
    rd_pntr <= 'd0;
  else
    rd_pntr <= rd_pntr_next;

//bin2gary
assign wr_pntr_gray = wr_pntr[ADDR_WIDTH:0] ^ {1'b0,wr_pntr[ADDR_WIDTH:1]};
assign rd_pntr_gray = rd_pntr[ADDR_WIDTH:0] ^ {1'b0,rd_pntr[ADDR_WIDTH:1]};

always@(posedge wrclk or posedge reset)
  if(reset)
    wr_pntr_gray_reg <= 'd0;
  else
    wr_pntr_gray_reg <= wr_pntr_gray;

always@(posedge rdclk or posedge reset)
  if(reset)
    rd_pntr_gray_reg <= 'd0;
  else
    rd_pntr_gray_reg <= rd_pntr_gray;

//wrside  ---->  rdside
always@(posedge rdclk)
begin
  rdside_wr_pntr_gray <= wr_pntr_gray_reg;
  rdside_wr_pntr_gray_dly1 <= rdside_wr_pntr_gray;
end

//rdside  ---->  wrside
always@(posedge wrclk)
begin
  wrside_rd_pntr_gray <= rd_pntr_gray_reg;
  wrside_rd_pntr_gray_dly1 <= wrside_rd_pntr_gray;
end

//gary2bin,rdside
assign rdside_wr_pntr_bin[ADDR_WIDTH] = rdside_wr_pntr_gray_dly1[ADDR_WIDTH];

genvar i;
generate
  for(i = 0; i < ADDR_WIDTH; i = i + 1) begin : gray2bin_inst0
    assign rdside_wr_pntr_bin[i] = rdside_wr_pntr_bin[i+1] ^ rdside_wr_pntr_gray_dly1[i];
  end
endgenerate

//gary2bin,wrside
assign wrside_rd_pntr_bin[ADDR_WIDTH] = wrside_rd_pntr_gray_dly1[ADDR_WIDTH];

genvar j;
generate
  for(j = 0; j < ADDR_WIDTH; j = j + 1) begin : gray2bin_inst1
    assign wrside_rd_pntr_bin[j] = wrside_rd_pntr_bin[j+1] ^ wrside_rd_pntr_gray_dly1[j];
  end
endgenerate

assign rdusedw = rdside_wr_pntr_bin - rd_pntr;
assign wrusedw = wr_pntr - wrside_rd_pntr_bin;

always@(posedge rdclk or posedge reset)
begin
  if(reset)
    empty_pre <= 1'b1;
  else
    empty_pre <= (rdside_wr_pntr_bin[ADDR_WIDTH:0] == rd_pntr_next[ADDR_WIDTH:0]);
end

always@(posedge rdclk or posedge reset)
begin
  if(reset)
    empty_pre_dly1 <= 1'b1;
  else
    empty_pre_dly1 <= empty_pre;
end

assign empty = empty_pre | empty_pre_dly1 ;

always@(posedge wrclk or posedge reset)
begin
  if(reset)
    full <= 1'b0;
  else
    full <= ( wrside_rd_pntr_bin[ADDR_WIDTH] != wr_pntr_next[ADDR_WIDTH] ) &&
            ( wrside_rd_pntr_bin[ADDR_WIDTH-1:0] == wr_pntr_next[ADDR_WIDTH-1:0]);
end

//when almost_empty is not asserted, there are no less than FULL_AHEAD words can to be write into FIFO.
always@(posedge wrclk or posedge reset)
begin
  if(reset)
    almost_full <= 1'b0;
  else
    almost_full <= ((wr_pntr_next[ADDR_WIDTH:0] - wrside_rd_pntr_bin[ADDR_WIDTH:0] ) >= almost_full_threshold);
end


endmodule

16. async_fifo/async_fifo.v
`timescale 1ns / 1ps
// 模块: async_fifo
// 说明: 异步 FIFO 顶层封装，包含控制逻辑与双口 RAM，用于跨时钟域安全传输数据。
// 主要参数:
//  - DATA_WIDTH: 数据宽度
//  - ADDR_WIDTH: 地址宽度（决定 FIFO 深度）
//  - FULL_AHEAD / SHOWAHEAD_EN: FIFO 行为配置
// 主要端口:
//  - reset: 异步复位（高电平有效）
//  - wrclk/wren/wrdata: 写端口（写时钟域）
//  - rdclk/rden/rddata: 读端口（读时钟域）
//  - full/empty/wrusedw/rdusedw: 状态指示
// 说明/备注:
//  - 使用 `async_fifo_ctrl` 负责读写指针同步和状态生成，底层使用 `dpram` 实现存储。
// -----------------------------------------------------------------------------
module async_fifo #(
  parameter DATA_WIDTH   = 16,
  parameter ADDR_WIDTH   = 16,
  parameter FULL_AHEAD   = 1,
  parameter SHOWAHEAD_EN = 0
)
(
  input                    reset,
  //fifo wr
  input                    wrclk,
  input                    wren,
  input   [DATA_WIDTH-1:0] wrdata,
  output                   full,
  output                   almost_full,
  output  [ADDR_WIDTH:0]   wrusedw,
  //fifo rd
  input                    rdclk,
  input                    rden,
  output  [DATA_WIDTH-1:0] rddata,
  output                   empty,
  output  [ADDR_WIDTH:0]   rdusedw
);

wire  [DATA_WIDTH-1:0] ram_dout;
wire  [ADDR_WIDTH-1:0] ram_wraddr;
wire  [ADDR_WIDTH-1:0] ram_rdaddr;
wire  [DATA_WIDTH-1:0] ram_din;
wire                   ram_wren;

wire  [DATA_WIDTH-1:0] rddata_tmp;
reg   [DATA_WIDTH-1:0] rddata_tmp_latch;

always@(posedge rdclk or posedge reset)
  if(reset)
    rddata_tmp_latch <= 'd0;
  else if(rden)
    rddata_tmp_latch <= rddata_tmp;

generate
  if(SHOWAHEAD_EN) begin: inst0
  //
    assign rddata = rddata_tmp;
  //
  end
  else begin: inst1
  //
    assign rddata = rddata_tmp_latch;
  //
  end
endgenerate

async_fifo_ctrl #(
  .DATA_WIDTH (DATA_WIDTH ),
  .ADDR_WIDTH (ADDR_WIDTH ),
  .FULL_AHEAD (FULL_AHEAD )
)async_fifo_ctrl_inst
(
  .reset       (reset       ),
  //fifo wr
  .wrclk       (wrclk       ),
  .wren        (wren        ),
  .wrdata      (wrdata      ),
  .full        (full        ),
  .almost_full (almost_full ),
  .wrusedw     (wrusedw     ),
  //fifo rd
  .rdclk       (rdclk       ),
  .rden        (rden        ),
  .rddata      (rddata_tmp  ),
  .empty       (empty       ),
  .rdusedw     (rdusedw     ),
  //ram
  .ram_dout    (ram_dout    ),
  .ram_wraddr  (ram_wraddr  ),
  .ram_rdaddr  (ram_rdaddr  ),
  .ram_din     (ram_din     ),
  .ram_wren    (ram_wren    )
);

dpram #(
  .DATA_WIDTH (DATA_WIDTH ),
  .ADDR_WIDTH (ADDR_WIDTH )
)dpram_inst
(
  .wrclock   (wrclk      ),
  .wren      (ram_wren   ),
  .wraddress (ram_wraddr ),
  .data      (ram_din    ),
  .rdclock   (rdclk      ),
  .rden      (1'b1       ),
  .rdaddress (ram_rdaddr ),
  .q         (ram_dout   )
);


endmodule

16. async_fifo/async_fifo_tb.v
`timescale 1ns / 1ps
// 模块: async_fifo_tb
// 说明: 异步 FIFO 功能仿真
//       - 使用小参数（DATA_WIDTH=8, ADDR_WIDTH=4, 深度16）加速仿真
//       - 写时钟 100MHz，读时钟 75MHz（跨时钟域）
//       - 场景：写满→full标志；顺序读验证数据；空→empty标志

module async_fifo_tb;

  localparam DW   = 8;
  localparam AW   = 4;   // 深度 2^4 = 16
  localparam DEPTH = (1 << AW);

  // 写时钟 100MHz (10ns), 读时钟 75MHz (~13.3ns)
  localparam WR_HALF = 5;
  localparam RD_HALF = 7;

  reg         reset;
  reg         wrclk, rdclk;
  reg         wren,  rden;
  reg  [DW-1:0] wrdata;
  wire [DW-1:0] rddata;
  wire          full, almost_full, empty;
  wire [AW:0]   wrusedw, rdusedw;

  async_fifo #(
    .DATA_WIDTH(DW),
    .ADDR_WIDTH(AW),
    .FULL_AHEAD(1),
    .SHOWAHEAD_EN(0)
  ) dut (
    .reset      (reset),
    .wrclk      (wrclk),
    .wren       (wren),
    .wrdata     (wrdata),
    .full       (full),
    .almost_full(almost_full),
    .wrusedw    (wrusedw),
    .rdclk      (rdclk),
    .rden       (rden),
    .rddata     (rddata),
    .empty      (empty),
    .rdusedw    (rdusedw)
  );

  // 时钟生成
  initial wrclk = 0;
  always #WR_HALF wrclk = ~wrclk;
  initial rdclk = 0;
  always #RD_HALF rdclk = ~rdclk;

  integer err = 0;
  integer i;
  reg [DW-1:0] exp_data [0:DEPTH-1];

  initial begin
    $dumpfile("async_fifo_tb.vcd");
    $dumpvars(0, async_fifo_tb);

    reset  = 1;
    wren   = 0;
    rden   = 0;
    wrdata = 0;

    repeat(5) @(posedge wrclk);
    reset = 0;
    repeat(3) @(posedge wrclk);

    // ── 场景1：写入 DEPTH 个数据直到 full ────────────────
    $display("[场景1] 顺序写入 %0d 个数据", DEPTH);
    for (i = 0; i < DEPTH; i = i + 1) begin
      @(negedge wrclk);
      if (!full) begin
        wren   <= 1'b1;
        wrdata <= i[DW-1:0];
        exp_data[i] = i[DW-1:0];
      end else begin
        $display("[INFO] full at i=%0d", i);
      end
      @(posedge wrclk); #1;
    end
    @(negedge wrclk); wren <= 0;
    repeat(5) @(posedge wrclk);

    if (full)
      $display("[PASS] full 标志正确拉高");
    else begin
      $display("[FAIL] 写满后 full 未拉高");
      err = err + 1;
    end

    // ── 场景2：顺序读出，验证数据 ─────────────────────────
    $display("[场景2] 顺序读出并验证数据");
    for (i = 0; i < DEPTH; i = i + 1) begin
      @(negedge rdclk);
      if (!empty) begin
        rden <= 1'b1;
      end
      @(posedge rdclk); #1;
      @(negedge rdclk);
      rden <= 1'b0;
      @(posedge rdclk); #1;
      if (rddata !== exp_data[i]) begin
        $display("[FAIL] 第%0d个数据: 期望0x%02h 实际0x%02h", i, exp_data[i], rddata);
        err = err + 1;
      end
    end
    repeat(10) @(posedge rdclk);

    if (empty)
      $display("[PASS] empty 标志正确拉高");
    else begin
      $display("[FAIL] 读空后 empty 未拉高");
      err = err + 1;
    end

    // ── 场景3：同时读写（wren=1, rden=1）─────────────────
    $display("[场景3] 同时读写验证");
    @(negedge wrclk);
    wren   <= 1'b1;
    wrdata <= 8'hAB;
    @(posedge wrclk);
    @(negedge wrclk); wren <= 0;
    repeat(10) @(posedge rdclk);

    @(negedge rdclk); rden <= 1'b1;
    @(posedge rdclk); #1;
    @(negedge rdclk); rden <= 0;
    @(posedge rdclk); #1;
    if (rddata === 8'hAB)
      $display("[PASS] 同时读写：读出 0x%02h", rddata);
    else begin
      $display("[FAIL] 同时读写：期望 0xAB，实际 0x%02h", rddata);
      err = err + 1;
    end

    repeat(10) @(posedge wrclk);

    if (err == 0)
      $display("[RESULT] async_fifo 全部测试通过！");
    else
      $display("[RESULT] async_fifo 存在 %0d 个错误", err);

    $finish;
  end

  initial begin
    #500_000;
    $display("[TIMEOUT] async_fifo 仿真超时");
    $finish;
  end
endmodule

16. async_fifo/async_fifo_tb.vcd
$date
	Wed Feb 18 21:31:58 2026
$end
$version
	Icarus Verilog
$end
$timescale
	1ps
$end
$scope module async_fifo_tb $end
$var wire 5 ! wrusedw [4:0] $end
$var wire 5 " rdusedw [4:0] $end
$var wire 8 # rddata [7:0] $end
$var wire 1 $ full $end
$var wire 1 % empty $end
$var wire 1 & almost_full $end
$var reg 1 ' rdclk $end
$var reg 1 ( rden $end
$var reg 1 ) reset $end
$var reg 1 * wrclk $end
$var reg 8 + wrdata [7:0] $end
$var reg 1 , wren $end
$var integer 32 - err [31:0] $end
$var integer 32 . i [31:0] $end
$scope module dut $end
$var wire 1 ' rdclk $end
$var wire 1 ( rden $end
$var wire 1 ) reset $end
$var wire 1 * wrclk $end
$var wire 8 / wrdata [7:0] $end
$var wire 1 , wren $end
$var wire 5 0 wrusedw [4:0] $end
$var wire 5 1 rdusedw [4:0] $end
$var wire 8 2 rddata_tmp [7:0] $end
$var wire 8 3 rddata [7:0] $end
$var wire 1 4 ram_wren $end
$var wire 4 5 ram_wraddr [3:0] $end
$var wire 4 6 ram_rdaddr [3:0] $end
$var wire 8 7 ram_dout [7:0] $end
$var wire 8 8 ram_din [7:0] $end
$var wire 1 $ full $end
$var wire 1 % empty $end
$var wire 1 & almost_full $end
$var reg 8 9 rddata_tmp_latch [7:0] $end
$scope begin inst1 $end
$upscope $end
$scope module async_fifo_ctrl_inst $end
$var wire 5 : almost_full_threshold [4:0] $end
$var wire 1 % empty $end
$var wire 8 ; ram_din [7:0] $end
$var wire 1 4 ram_wren $end
$var wire 5 < rd_pntr_gray [4:0] $end
$var wire 1 ' rdclk $end
$var wire 8 = rddata [7:0] $end
$var wire 1 ( rden $end
$var wire 1 ) reset $end
$var wire 5 > wr_pntr_gray [4:0] $end
$var wire 1 * wrclk $end
$var wire 8 ? wrdata [7:0] $end
$var wire 1 , wren $end
$var wire 5 @ wrusedw [4:0] $end
$var wire 5 A wrside_rd_pntr_bin [4:0] $end
$var wire 5 B wr_pntr_next [4:0] $end
$var wire 5 C rdusedw [4:0] $end
$var wire 5 D rdside_wr_pntr_bin [4:0] $end
$var wire 5 E rd_pntr_next [4:0] $end
$var wire 4 F ram_wraddr [3:0] $end
$var wire 4 G ram_rdaddr [3:0] $end
$var wire 8 H ram_dout [7:0] $end
$var reg 1 & almost_full $end
$var reg 1 I empty_pre $end
$var reg 1 J empty_pre_dly1 $end
$var reg 1 $ full $end
$var reg 5 K rd_pntr [4:0] $end
$var reg 5 L rd_pntr_gray_reg [4:0] $end
$var reg 5 M rdside_wr_pntr_gray [4:0] $end
$var reg 5 N rdside_wr_pntr_gray_dly1 [4:0] $end
$var reg 5 O wr_pntr [4:0] $end
$var reg 5 P wr_pntr_gray_reg [4:0] $end
$var reg 5 Q wrside_rd_pntr_gray [4:0] $end
$var reg 5 R wrside_rd_pntr_gray_dly1 [4:0] $end
$scope begin gray2bin_inst0[0] $end
$upscope $end
$scope begin gray2bin_inst0[1] $end
$upscope $end
$scope begin gray2bin_inst0[2] $end
$upscope $end
$scope begin gray2bin_inst0[3] $end
$upscope $end
$scope begin gray2bin_inst1[0] $end
$upscope $end
$scope begin gray2bin_inst1[1] $end
$upscope $end
$scope begin gray2bin_inst1[2] $end
$upscope $end
$scope begin gray2bin_inst1[3] $end
$upscope $end
$upscope $end
$scope module dpram_inst $end
$var wire 8 S data [7:0] $end
$var wire 4 T rdaddress [3:0] $end
$var wire 1 ' rdclock $end
$var wire 1 U rden $end
$var wire 4 V wraddress [3:0] $end
$var wire 1 * wrclock $end
$var wire 1 4 wren $end
$var wire 8 W q [7:0] $end
$var reg 8 X q_wire [7:0] $end
$scope begin use_dram $end
$upscope $end
$upscope $end
$upscope $end
$upscope $end
$enddefinitions $end
#0
$dumpvars
bx X
bx W
b0 V
1U
b0 T
b0 S
bx R
bx Q
b0 P
b0 O
bx N
bx M
b0 L
b0 K
1J
1I
bx H
b0 G
b0 F
b0 E
bx D
bx C
b0 B
bx A
bx @
b0 ?
b0 >
bx =
b0 <
b0 ;
b1111 :
b0 9
b0 8
bx 7
b0 6
b0 5
04
b0 3
bx 2
bx 1
bx 0
b0 /
bx .
b0 -
0,
b0 +
0*
1)
0(
0'
0&
1%
0$
b0 #
bx "
bx !
$end
#5000
b0 Q
1*
#7000
b0 M
1'
#10000
0*
#14000
0'
#15000
b0 !
b0 0
b0 @
b0 A
b0 R
1*
#20000
0*
#21000
b0 "
b0 1
b0 C
b0 D
b0 N
1'
#25000
1*
#28000
0'
#30000
0*
#35000
1*
1'
#40000
0*
#42000
0'
#45000
0)
1*
#49000
1'
#50000
0*
#55000
1*
#56000
0'
#60000
0*
#63000
1'
#65000
1*
#70000
0*
0'
#75000
b0 .
1*
#77000
1'
#80000
14
b1 B
1,
0*
#84000
0'
#85000
b1 5
b1 F
b1 V
b1 >
b10 B
b1 !
b1 0
b1 @
b1 O
1*
#86000
b1 .
#90000
b1 8
b1 ;
b1 S
b1 +
b1 /
b1 ?
0*
#91000
b0 2
b0 =
b0 7
b0 H
b0 W
b0 X
1'
#95000
b10 5
b10 F
b10 V
b11 >
b11 B
b10 !
b10 0
b10 @
b10 O
b1 P
1*
#96000
b10 .
#98000
0'
#100000
b10 8
b10 ;
b10 S
b10 +
b10 /
b10 ?
0*
#105000
b11 5
b11 F
b11 V
b10 >
b11 P
b100 B
b11 !
b11 0
b11 @
b11 O
b1 M
1*
1'
#106000
b11 .
#110000
b11 8
b11 ;
b11 S
b11 +
b11 /
b11 ?
0*
#112000
0'
#115000
b100 5
b100 F
b100 V
b110 >
b101 B
b100 !
b100 0
b100 @
b100 O
b10 P
1*
#116000
b100 .
#119000
b1 "
b1 1
b1 C
b1 D
b1 N
b10 M
1'
#120000
b100 8
b100 ;
b100 S
b100 +
b100 /
b100 ?
0*
#125000
b101 5
b101 F
b101 V
b111 >
b110 P
b110 B
b101 !
b101 0
b101 @
b101 O
1*
#126000
b101 .
0'
#130000
b101 8
b101 ;
b101 S
b101 +
b101 /
b101 ?
0*
#133000
b11 "
b11 1
b11 C
b11 D
0I
b10 N
b110 M
1'
#135000
b110 5
b110 F
b110 V
b101 >
b111 B
b110 !
b110 0
b110 @
b110 O
b111 P
1*
#136000
b110 .
#140000
b110 8
b110 ;
b110 S
b110 +
b110 /
b110 ?
0*
0'
#145000
b111 5
b111 F
b111 V
b100 >
b101 P
b1000 B
b111 !
b111 0
b111 @
b111 O
1*
#146000
b111 .
#147000
b100 "
b100 1
b100 C
b100 D
0%
0J
b110 N
b101 M
1'
#150000
b111 8
b111 ;
b111 S
b111 +
b111 /
b111 ?
0*
#154000
0'
#155000
b1000 5
b1000 F
b1000 V
b1100 >
b1001 B
b1000 !
b1000 0
b1000 @
b1000 O
b100 P
1*
#156000
b1000 .
#160000
b1000 8
b1000 ;
b1000 S
b1000 +
b1000 /
b1000 ?
0*
#161000
b110 "
b110 1
b110 C
b110 D
b101 N
b100 M
1'
#165000
b1001 5
b1001 F
b1001 V
b1101 >
b1100 P
b1010 B
b1001 !
b1001 0
b1001 @
b1001 O
1*
#166000
b1001 .
#168000
0'
#170000
b1001 8
b1001 ;
b1001 S
b1001 +
b1001 /
b1001 ?
0*
#175000
b111 "
b111 1
b111 C
b111 D
b1010 5
b1010 F
b1010 V
b1111 >
b1011 B
b1010 !
b1010 0
b1010 @
b1010 O
b1101 P
b100 N
b1100 M
1*
1'
#176000
b1010 .
#180000
b1010 8
b1010 ;
b1010 S
b1010 +
b1010 /
b1010 ?
0*
#182000
0'
#185000
b1011 5
b1011 F
b1011 V
b1110 >
b1111 P
b1100 B
b1011 !
b1011 0
b1011 @
b1011 O
1*
#186000
b1011 .
#189000
b1000 "
b1000 1
b1000 C
b1000 D
b1100 N
b1111 M
1'
#190000
b1011 8
b1011 ;
b1011 S
b1011 +
b1011 /
b1011 ?
0*
#195000
b1100 5
b1100 F
b1100 V
b1010 >
b1101 B
b1100 !
b1100 0
b1100 @
b1100 O
b1110 P
1*
#196000
b1100 .
0'
#200000
b1100 8
b1100 ;
b1100 S
b1100 +
b1100 /
b1100 ?
0*
#203000
b1010 "
b1010 1
b1010 C
b1010 D
b1111 N
b1110 M
1'
#205000
b1101 5
b1101 F
b1101 V
b1011 >
b1010 P
b1110 B
b1101 !
b1101 0
b1101 @
b1101 O
1*
#206000
b1101 .
#210000
b1101 8
b1101 ;
b1101 S
b1101 +
b1101 /
b1101 ?
0*
0'
#215000
b1110 5
b1110 F
b1110 V
b1001 >
b1111 B
b1110 !
b1110 0
b1110 @
b1110 O
b1011 P
1*
#216000
b1110 .
#217000
b1011 "
b1011 1
b1011 C
b1011 D
b1110 N
b1011 M
1'
#220000
b1110 8
b1110 ;
b1110 S
b1110 +
b1110 /
b1110 ?
0*
#224000
0'
#225000
b1111 5
b1111 F
b1111 V
b1000 >
1&
b1001 P
b10000 B
b1111 !
b1111 0
b1111 @
b1111 O
1*
#226000
b1111 .
#230000
b1111 8
b1111 ;
b1111 S
b1111 +
b1111 /
b1111 ?
0*
#231000
b1101 "
b1101 1
b1101 C
b1101 D
b1011 N
b1001 M
1'
#235000
b0 5
b0 F
b0 V
b11000 >
04
b10000 B
b10000 !
b10000 0
b10000 @
b10000 O
b1000 P
1$
1*
#236000
b10000 .
#238000
0'
#240000
0,
0*
#245000
b1110 "
b1110 1
b1110 C
b1110 D
b11000 P
b1001 N
b1000 M
1*
1'
#250000
0*
#252000
0'
#255000
1*
#259000
b1111 "
b1111 1
b1111 C
b1111 D
b1000 N
b11000 M
1'
#260000
0*
#265000
1*
#266000
0'
#270000
0*
#273000
b10000 "
b10000 1
b10000 C
b10000 D
b11000 N
1'
#275000
1*
#280000
0*
0'
#285000
b0 .
1*
#287000
1'
#290000
0*
#294000
b1 6
b1 G
b1 T
b1 E
1(
0'
#295000
1*
#300000
0*
#301000
b10 6
b10 G
b10 T
b1 <
b10 E
b1111 "
b1111 1
b1111 C
b1 K
b1 2
b1 =
b1 7
b1 H
b1 W
b1 X
1'
#305000
1*
#308000
b1 6
b1 G
b1 T
b1 E
0(
0'
#310000
0*
#315000
b1 L
1*
1'
#316000
b1 .
#320000
0*
#322000
b10 6
b10 G
b10 T
b10 E
1(
0'
#325000
b1 Q
1*
#329000
b11 6
b11 G
b11 T
b11 <
b11 E
b1110 "
b1110 1
b1110 C
b10 K
b1 #
b1 3
b1 9
b10 2
b10 =
b10 7
b10 H
b10 W
b10 X
1'
#330000
0*
#335000
b1111 !
b1111 0
b1111 @
b1 A
b1 R
1*
#336000
b10 6
b10 G
b10 T
b10 E
0(
0'
#340000
0*
#343000
b11 L
1'
#344000
b10 .
#345000
0$
b11 Q
1*
#350000
b11 6
b11 G
b11 T
b11 E
1(
0*
0'
#355000
b1110 !
b1110 0
b1110 @
b10 A
b11 R
1*
#357000
b100 6
b100 G
b100 T
b10 <
b100 E
b1101 "
b1101 1
b1101 C
b11 K
b10 #
b10 3
b10 9
b11 2
b11 =
b11 7
b11 H
b11 W
b11 X
1'
#360000
0*
#364000
b11 6
b11 G
b11 T
b11 E
0(
0'
#365000
0&
1*
#370000
0*
#371000
b10 L
1'
#372000
b11 .
#375000
b10 Q
1*
#378000
b100 6
b100 G
b100 T
b100 E
1(
0'
#380000
0*
#385000
b1101 !
b1101 0
b1101 @
b11 A
b101 6
b101 G
b101 T
b110 <
b10 R
b101 E
b1100 "
b1100 1
b1100 C
b100 K
b11 #
b11 3
b11 9
b100 2
b100 =
b100 7
b100 H
b100 W
b100 X
1*
1'
#390000
0*
#392000
b100 6
b100 G
b100 T
b100 E
0(
0'
#395000
1*
#399000
b110 L
1'
#400000
b100 .
0*
#405000
b110 Q
1*
#406000
b101 6
b101 G
b101 T
b101 E
1(
0'
#410000
0*
#413000
b110 6
b110 G
b110 T
b111 <
b110 E
b1011 "
b1011 1
b1011 C
b101 K
b100 #
b100 3
b100 9
b101 2
b101 =
b101 7
b101 H
b101 W
b101 X
1'
#415000
b1100 !
b1100 0
b1100 @
b100 A
b110 R
1*
#420000
b101 6
b101 G
b101 T
b101 E
0(
0*
0'
#425000
1*
#427000
b111 L
1'
#428000
b101 .
#430000
0*
#434000
b110 6
b110 G
b110 T
b110 E
1(
0'
#435000
b111 Q
1*
#440000
0*
#441000
b111 6
b111 G
b111 T
b101 <
b111 E
b1010 "
b1010 1
b1010 C
b110 K
b101 #
b101 3
b101 9
b110 2
b110 =
b110 7
b110 H
b110 W
b110 X
1'
#445000
b1011 !
b1011 0
b1011 @
b101 A
b111 R
1*
#448000
b110 6
b110 G
b110 T
b110 E
0(
0'
#450000
0*
#455000
b101 L
1*
1'
#456000
b110 .
#460000
0*
#462000
b111 6
b111 G
b111 T
b111 E
1(
0'
#465000
b101 Q
1*
#469000
b1000 6
b1000 G
b1000 T
b100 <
b1000 E
b1001 "
b1001 1
b1001 C
b111 K
b110 #
b110 3
b110 9
b111 2
b111 =
b111 7
b111 H
b111 W
b111 X
1'
#470000
0*
#475000
b1010 !
b1010 0
b1010 @
b110 A
b101 R
1*
#476000
b111 6
b111 G
b111 T
b111 E
0(
0'
#480000
0*
#483000
b100 L
1'
#484000
b111 .
#485000
b100 Q
1*
#490000
b1000 6
b1000 G
b1000 T
b1000 E
1(
0*
0'
#495000
b1001 !
b1001 0
b1001 @
b111 A
b100 R
1*
#497000
b1001 6
b1001 G
b1001 T
b1100 <
b1001 E
b1000 "
b1000 1
b1000 C
b1000 K
b111 #
b111 3
b111 9
b1000 2
b1000 =
b1000 7
b1000 H
b1000 W
b1000 X
1'
#500000
0*
#504000
b1000 6
b1000 G
b1000 T
b1000 E
0(
0'
#505000
1*
#510000
0*
#511000
b1100 L
1'
#512000
b1000 .
#515000
b1100 Q
1*
#518000
b1001 6
b1001 G
b1001 T
b1001 E
1(
0'
#520000
0*
#525000
b1000 !
b1000 0
b1000 @
b1000 A
b1010 6
b1010 G
b1010 T
b1101 <
b1100 R
b1010 E
b111 "
b111 1
b111 C
b1001 K
b1000 #
b1000 3
b1000 9
b1001 2
b1001 =
b1001 7
b1001 H
b1001 W
b1001 X
1*
1'
#530000
0*
#532000
b1001 6
b1001 G
b1001 T
b1001 E
0(
0'
#535000
1*
#539000
b1101 L
1'
#540000
b1001 .
0*
#545000
b1101 Q
1*
#546000
b1010 6
b1010 G
b1010 T
b1010 E
1(
0'
#550000
0*
#553000
b1011 6
b1011 G
b1011 T
b1111 <
b1011 E
b110 "
b110 1
b110 C
b1010 K
b1001 #
b1001 3
b1001 9
b1010 2
b1010 =
b1010 7
b1010 H
b1010 W
b1010 X
1'
#555000
b111 !
b111 0
b111 @
b1001 A
b1101 R
1*
#560000
b1010 6
b1010 G
b1010 T
b1010 E
0(
0*
0'
#565000
1*
#567000
b1111 L
1'
#568000
b1010 .
#570000
0*
#574000
b1011 6
b1011 G
b1011 T
b1011 E
1(
0'
#575000
b1111 Q
1*
#580000
0*
#581000
b1100 6
b1100 G
b1100 T
b1110 <
b1100 E
b101 "
b101 1
b101 C
b1011 K
b1010 #
b1010 3
b1010 9
b1011 2
b1011 =
b1011 7
b1011 H
b1011 W
b1011 X
1'
