01. mux2/mux2.v
module mux2(
  a,
  b,
  sel,
  out
);

  input a;
  input b;
  input sel;
  output out;
  
  assign out = (sel==0)?a:b;
 
endmodule

01. mux2/mux2_tb.v
`timescale 1ns / 1ns

module mux2_tb();

  reg  S0, S1, S2;
  wire mux2_out;

  mux2 mux2_inst0(
    .a  (S0),
    .b  (S1),
    .sel(S2),
    .out(mux2_out)
  );

  integer err = 0;

  task check;
    input exp;
    begin
      #1;
      if (mux2_out !== exp) begin
        $display("[FAIL] sel=%b a=%b b=%b => out=%b (exp %b)", S2, S0, S1, mux2_out, exp);
        err = err + 1;
      end
    end
  endtask

  initial begin
    // sel=0 时输出 a
    S2=0; S1=0; S0=0; #10; check(0);
    S2=0; S1=0; S0=1; #10; check(1);
    S2=0; S1=1; S0=0; #10; check(0);
    S2=0; S1=1; S0=1; #10; check(1);
    // sel=1 时输出 b
    S2=1; S1=0; S0=0; #10; check(0);
    S2=1; S1=0; S0=1; #10; check(0);
    S2=1; S1=1; S0=0; #10; check(1);
    S2=1; S1=1; S0=1; #10; check(1);

    if (err == 0)
      $display("[PASS] mux2 全部8组输入验证通过");
    else
      $display("[FAIL] mux2 出错 %0d 组", err);
    $finish;
  end

  initial begin
    $dumpfile("mux2_tb.vcd");
    $dumpvars(0, mux2_tb);
  end
endmodule

01. mux2/mux2_tb.vcd
$date
	Wed Feb 18 21:26:32 2026
$end
$version
	Icarus Verilog
$end
$timescale
	1ns
$end
$scope module mux2_tb $end
$var wire 1 ! mux2_out $end
$var reg 1 " S0 $end
$var reg 1 # S1 $end
$var reg 1 $ S2 $end
$var integer 32 % err [31:0] $end
$scope module mux2_inst0 $end
$var wire 1 " a $end
$var wire 1 # b $end
$var wire 1 $ sel $end
$var wire 1 ! out $end
$upscope $end
$scope task check $end
$var reg 1 & exp $end
$upscope $end
$upscope $end
$enddefinitions $end
#0
$dumpvars
x&
b0 %
0$
0#
0"
0!
$end
#10
0&
#11
1!
1"
#21
1&
#22
0!
0"
1#
#32
0&
#33
1!
1"
#43
1&
#44
0!
0"
0#
1$
#54
0&
#55
1"
#66
1!
0"
1#
#76
1&
#77
1"
