07. key_filter/key_filter_para3.v
`timescale 1ns / 1ps
//////////////////////////////////////////////////////////////////////////////////
// Company: NJUPT
// Engineer: Lucian
//
// Create Date: 2025/08/19 15:33:14
// Design Name:
// Module Name: key_filter_para3
// Project Name:
// Target Devices:
// Tool Versions:
// Description:
//
// Dependencies:
//
// Revision:
// Revision 0.01 - File Created
// Additional Comments:
//
//////////////////////////////////////////////////////////////////////////////////


module key_filter_para3 (
        input  wire        clk,          // 系统时钟
        input  wire        rst_n,        // 异步复位，低电平有效
        input  wire        key,          // 原始按键输入 (低电平为按下)

        output reg         key_p_flag,   // 按键按下标志 (单周期脉冲)
        output reg         key_r_flag,   // 按键释放标志 (单周期脉冲)
        output reg         key_state     // 消抖后的稳定按键状态 (1:释放, 0:按下)
    );

    // 消抖时间参数 (以50MHz时钟为例，20ms)
    parameter DEBOUNCE_TIME = 20'd1_000_000;

    // 状态机状态定义
    localparam S_IDLE        = 2'b00;    // 空闲状态
    localparam S_P_FILTER    = 2'b01;    // 按下消抖
    localparam S_WAIT_R      = 2'b10;    // 等待释放
    localparam S_R_FILTER    = 2'b11;    // 释放消抖

    // 输入同步及边沿检测
    reg  [1:0] r_key;
    wire       pedge_key; // 上升沿 (释放)
    wire       nedge_key; // 下降沿 (按下)

    // 状态机寄存器
    reg  [1:0] current_state;
    reg  [1:0] next_state;

    // 消抖计数器
    reg  [19:0] cnt;


    always @(posedge clk or negedge rst_n) begin
        if (!rst_n)
            r_key <= 2'b11;
        else
            r_key <= {r_key[0], key};
    end

    assign nedge_key = (r_key == 2'b10);
    assign pedge_key = (r_key == 2'b01);

    // 段一：次态逻辑 (组合逻辑)
    // 职责：只根据当前状态和输入，决定下一个状态是什么。
    always @(*) begin
        // 黄金法则：为 next_state 提供默认值，防止产生latch
        next_state = current_state;

        case (current_state)
            S_IDLE: begin
                if (nedge_key) begin
                    next_state = S_P_FILTER;
                end
            end
            S_P_FILTER: begin
                if (pedge_key) begin // 抖动，返回IDLE
                    next_state = S_IDLE;
                end
                else if (cnt >= DEBOUNCE_TIME - 1) begin // 消抖成功
                    next_state = S_WAIT_R;
                end
            end
            S_WAIT_R: begin
                if (pedge_key) begin
                    next_state = S_R_FILTER;
                end
            end
            S_R_FILTER: begin
                if (nedge_key) begin // 抖动，返回WAIT_R
                    next_state = S_WAIT_R;
                end
                else if (cnt >= DEBOUNCE_TIME - 1) begin // 消抖成功
                    next_state = S_IDLE;
                end
            end
            default: begin
                next_state = S_IDLE;
            end
        endcase
    end

    // 段二：状态更新 (时序逻辑) -- 状态机的“心脏”
    // 职责：只在时钟沿，用 next_state 更新 current_state。

    always @(posedge clk or negedge rst_n) begin
        if (!rst_n) begin
            current_state <= S_IDLE;
        end
        else begin
            current_state <= next_state;
        end
    end


    // 段三：输出与动作逻辑 (时序逻辑) -- 翻译状态图的“圆圈”和“动作”
    // 职责：只根据当前状态，决定输出信号和内部寄存器(如cnt)的行为。
    always @(posedge clk or negedge rst_n) begin
        if (!rst_n) begin
            key_p_flag <= 1'b0;
            key_r_flag <= 1'b0;
            key_state  <= 1'b1; // 初始为释放状态
            cnt        <= 20'd0;
        end
        else begin
            // 默认将脉冲信号拉低，只在特定切换瞬间拉高一拍
            key_p_flag <= 1'b0;
            key_r_flag <= 1'b0;

            case (current_state)
                S_IDLE: begin
                    key_state <= 1'b1;
                    cnt       <= 20'd0;
                end
                S_P_FILTER: begin
                    key_state <= 1'b1; // 消抖期间，稳定状态仍是“释放”
                    if (pedge_key) begin
                        cnt <= 20'd0; // 抖动，计数器清零
                    end
                    else if (cnt >= DEBOUNCE_TIME - 1) begin
                        key_p_flag <= 1'b1; // 在切换前一刻，产生按下脉冲
                        cnt        <= 20'd0;
                    end
                    else begin
                        cnt <= cnt + 1'b1; // 持续计时
                    end
                end
                S_WAIT_R: begin
                    key_state <= 1'b0; // 稳定按下
                    cnt       <= 20'd0;
                end
                S_R_FILTER: begin
                    key_state <= 1'b0; // 消抖期间，稳定状态仍是“按下”
                    if (nedge_key) begin
                        cnt <= 20'd0; // 抖动，计数器清零
                    end
                    else if (cnt >= DEBOUNCE_TIME - 1) begin
                        key_r_flag <= 1'b1; // 在切换前一刻，产生释放脉冲
                        cnt        <= 20'd0;
                    end
                    else begin
                        cnt <= cnt + 1'b1; // 持续计时
                    end
                end
                default: begin
                    key_state <= 1'b1;
                    cnt       <= 20'd0;
                end
            endcase
        end
    end

endmodule

07. key_filter/key_filter_para1.v
`timescale 1ns / 1ps
//////////////////////////////////////////////////////////////////////////////////
// Company:  NJUPT
// Engineer: Lucian
//
// Create Date: 2025/08/17 17:36:58
// Design Name:
// Module Name: key_filter
// Project Name:
// Target Devices:
// Tool Versions:
// Description:
//
// Dependencies:
//
// Revision:
// Revision 0.01 - File Created
// Additional Comments:
//
//////////////////////////////////////////////////////////////////////////////////
module key_filter (
        input  wire clk,
        input  wire rst_n,
        input  wire key,
        output reg  key_p_flag,
        output reg  key_r_flag,
        output reg  key_state
    );

    // 消抖时间参数 (20ms at 50MHz clock)
    parameter DEBOUNCE_TIME = 20'd1000000;

    reg [1:0] r_key;

    always @(posedge clk or negedge rst_n) begin
        if (!rst_n) begin
            r_key <= 2'b11;  // 复位时初始化为按键释放状态
        end
        else begin
            r_key <= {r_key[0], key};
        end
    end
    wire pedge_key;
    assign pedge_key = (r_key == 2'b01);
    wire nedge_key;
    assign nedge_key = (r_key == 2'b10);

    localparam IDLE = 2'b00;
    localparam P_FILTER = 2'b01;
    localparam WAIT_R = 2'b10;
    localparam R_FILTER = 2'b11;
    reg [19:0] cnt;
    reg [ 1:0] state;

    always @(posedge clk or negedge rst_n) begin
        if (!rst_n) begin
            state <= IDLE;
            key_p_flag <= 1'b0;
            key_r_flag <= 1'b0;
            key_state <= 1'b1;  // 初始状态为按键释放
            cnt <= 20'd0;
        end
        else begin
            case (state)
                IDLE: begin
                    key_r_flag <= 1'b0;
                    cnt <= 20'd0;  // 在IDLE状态清零计数器
                    if (nedge_key)
                        state <= P_FILTER;
                    else
                        state <= IDLE;
                end
                P_FILTER:
                    if ((pedge_key) && (cnt < DEBOUNCE_TIME - 1)) begin
                        state <= IDLE;
                        cnt <= 20'd0;  // 状态转换时清零计数器
                    end
                    else if (cnt >= DEBOUNCE_TIME - 1) begin
                        state <= WAIT_R;
                        key_p_flag <= 1'b1;
                        key_state <= 1'b0;  // 统一使用<=操作符
                        cnt <= 20'd0;  // 状态转换时清零计数器
                    end
                    else begin
                        state <= P_FILTER;
                        cnt <= cnt + 1'b1;
                    end

                WAIT_R: begin
                    key_p_flag <= 1'b0;
                    cnt <= 20'd0;  // 在WAIT_R状态保持计数器清零
                    if (pedge_key)
                        state <= R_FILTER;
                    else
                        state <= WAIT_R;
                end
                R_FILTER:
                    if ((nedge_key) && (cnt <= DEBOUNCE_TIME - 1)) begin
                        state <= WAIT_R;
                        cnt <= 20'd0;  // 状态转换时清零计数器
                    end
                    else if (cnt >= DEBOUNCE_TIME - 1) begin
                        state <= IDLE;
                        key_r_flag <= 1'b1;
                        cnt <= 20'd0;  // 统一使用<=操作符，状态转换时清零
                        key_state <= 1'b1;  // 统一使用<=操作符
                    end
                    else begin
                        state <= R_FILTER;
                        cnt <= cnt + 1'b1;
                    end
            endcase
        end
    end

endmodule

07. key_filter/key_filter_tb.v
`timescale 1ns / 1ps
// 模块: key_filter_tb
// 说明: 测试 key_filter_para1 / key_filter_para3 消抖逻辑
//       DEBOUNCE_TIME 通过 defparam 缩短为 100 周期加速仿真

module key_filter_tb;

  localparam DEBOUNCE_SIM = 20'd100;
  localparam CLK_HALF     = 10;   // 20ns 周期，50MHz

  reg  clk, rst_n, key;

  // para1（一段式时序输出）
  wire p1_flag, r1_flag, s1;
  key_filter u1 (
    .clk(clk), .rst_n(rst_n), .key(key),
    .key_p_flag(p1_flag), .key_r_flag(r1_flag), .key_state(s1)
  );
  defparam u1.DEBOUNCE_TIME = DEBOUNCE_SIM;

  // para3（标准三段式）
  wire p3_flag, r3_flag, s3;
  key_filter_para3 u3 (
    .clk(clk), .rst_n(rst_n), .key(key),
    .key_p_flag(p3_flag), .key_r_flag(r3_flag), .key_state(s3)
  );
  defparam u3.DEBOUNCE_TIME = DEBOUNCE_SIM;

  always #CLK_HALF clk = ~clk;

  integer err;
  integer t;

  initial begin
    $dumpfile("key_filter_tb.vcd");
    $dumpvars(0, key_filter_tb);

    clk   = 0;
    rst_n = 0;
    key   = 1;
    err   = 0;
    repeat(5) @(posedge clk);
    rst_n = 1;
    repeat(5) @(posedge clk);

    // ─────────────────────────────────────────────────────────
    // 场景1：稳定按下 超过消抖时间 → key_p_flag 脉冲, key_state=0
    // ─────────────────────────────────────────────────────────
    $display("[场景1] 稳定按下...");
    key = 0;

    // 等 para1 key_p_flag
    t = 0;
    while (!p1_flag && t < 5000) begin @(posedge clk); t = t + 1; end
    if (p1_flag) $display("[PASS] para1: key_p_flag 脉冲");
    else begin    $display("[FAIL] para1: key_p_flag 超时"); err = err+1; end

    // 等 para1 key_state=0
    t = 0;
    while (s1 !== 1'b0 && t < 5000) begin @(posedge clk); t = t + 1; end
    if (s1 === 1'b0) $display("[PASS] para1: key_state=0（按下稳定）");
    else begin       $display("[FAIL] para1: key_state 未变0"); err = err+1; end

    // 等 para3 key_p_flag
    t = 0;
    while (!p3_flag && t < 5000) begin @(posedge clk); t = t + 1; end
    if (p3_flag) $display("[PASS] para3: key_p_flag 脉冲");
    else begin   $display("[FAIL] para3: key_p_flag 超时"); err = err+1; end

    // 等 para3 key_state=0
    t = 0;
    while (s3 !== 1'b0 && t < 5000) begin @(posedge clk); t = t + 1; end
    if (s3 === 1'b0) $display("[PASS] para3: key_state=0（按下稳定）");
    else begin       $display("[FAIL] para3: key_state 未变0"); err = err+1; end

    // ─────────────────────────────────────────────────────────
    // 场景2：稳定释放 超过消抖时间 → key_r_flag 脉冲, key_state=1
    // ─────────────────────────────────────────────────────────
    $display("[场景2] 稳定释放...");
    key = 1;

    // 等 para1 key_r_flag
    t = 0;
    while (!r1_flag && t < 5000) begin @(posedge clk); t = t + 1; end
    if (r1_flag) $display("[PASS] para1: key_r_flag 脉冲");
    else begin   $display("[FAIL] para1: key_r_flag 超时"); err = err+1; end

    // 等 para1 key_state=1
    t = 0;
    while (s1 !== 1'b1 && t < 5000) begin @(posedge clk); t = t + 1; end
    if (s1 === 1'b1) $display("[PASS] para1: key_state=1（释放稳定）");
    else begin       $display("[FAIL] para1: key_state 未变1"); err = err+1; end

    // 等 para3 key_r_flag
    t = 0;
    while (!r3_flag && t < 5000) begin @(posedge clk); t = t + 1; end
    if (r3_flag) $display("[PASS] para3: key_r_flag 脉冲");
    else begin   $display("[FAIL] para3: key_r_flag 超时"); err = err+1; end

    // 等 para3 key_state=1
    t = 0;
    while (s3 !== 1'b1 && t < 5000) begin @(posedge clk); t = t + 1; end
    if (s3 === 1'b1) $display("[PASS] para3: key_state=1（释放稳定）");
    else begin       $display("[FAIL] para3: key_state 未变1"); err = err+1; end

    // ─────────────────────────────────────────────────────────
    // 场景3：短暂抖动（< 消抖时间）不应触发 key_p_flag
    // ─────────────────────────────────────────────────────────
    $display("[场景3] 短暂抖动（小于消抖时间）...");
    key = 0;
    repeat(DEBOUNCE_SIM / 2) @(posedge clk);   // 只等 1/2 消抖时间
    key = 1;                                     // 弹回
    repeat(DEBOUNCE_SIM + 50) @(posedge clk);
    // 此时不应有 key_p_flag（抖动已过，信号稳定为释放）
    @(posedge clk); #1;
    if (!p1_flag && !p3_flag)
      $display("[PASS] 场景3：抖动被正确过滤，key_p_flag 未误触发");
    else begin
      $display("[FAIL] 场景3：抖动未被过滤（p1=%b p3=%b）", p1_flag, p3_flag);
      err = err + 1;
    end

    repeat(5) @(posedge clk);

    if (err == 0)
      $display("[RESULT] key_filter 全部测试通过！");
    else
      $display("[RESULT] key_filter 存在 %0d 个错误", err);

    $finish;
  end

  initial begin
    #10_000_000;
    $display("[TIMEOUT] key_filter 仿真超时");
    $finish;
  end
endmodule

07. key_filter/key_filter_tb.vcd
$date
	Wed Feb 18 21:31:13 2026
$end
$version
	Icarus Verilog
$end
$timescale
	1ps
$end
$scope module key_filter_tb $end
$var wire 1 ! s3 $end
$var wire 1 " s1 $end
$var wire 1 # r3_flag $end
$var wire 1 $ r1_flag $end
$var wire 1 % p3_flag $end
$var wire 1 & p1_flag $end
$var reg 1 ' clk $end
$var reg 1 ( key $end
$var reg 1 ) rst_n $end
$var integer 32 * err [31:0] $end
$var integer 32 + t [31:0] $end
$scope module u1 $end
$var wire 1 ' clk $end
$var wire 1 ( key $end
$var wire 1 ) rst_n $end
$var wire 1 , pedge_key $end
$var wire 1 - nedge_key $end
$var reg 20 . cnt [19:0] $end
$var reg 1 & key_p_flag $end
$var reg 1 $ key_r_flag $end
$var reg 1 " key_state $end
$var reg 2 / r_key [1:0] $end
$var reg 2 0 state [1:0] $end
$upscope $end
$scope module u3 $end
$var wire 1 ' clk $end
$var wire 1 ( key $end
$var wire 1 ) rst_n $end
$var wire 1 1 pedge_key $end
$var wire 1 2 nedge_key $end
$var reg 20 3 cnt [19:0] $end
$var reg 2 4 current_state [1:0] $end
$var reg 1 % key_p_flag $end
$var reg 1 # key_r_flag $end
$var reg 1 ! key_state $end
$var reg 2 5 next_state [1:0] $end
$var reg 2 6 r_key [1:0] $end
$upscope $end
$upscope $end
$enddefinitions $end
#0
$dumpvars
b11 6
b0 5
b0 4
b0 3
02
01
b0 0
b11 /
b0 .
0-
0,
bx +
b0 *
0)
1(
0'
0&
0%
0$
0#
1"
1!
$end
#10000
1'
#20000
0'
#30000
1'
#40000
0'
#50000
1'
#60000
0'
#70000
1'
#80000
0'
#90000
1)
1'
#100000
0'
#110000
1'
#120000
0'
#130000
1'
#140000
0'
#150000
1'
#160000
0'
#170000
1'
#180000
0'
#190000
b1 5
1-
b10 /
12
b10 6
b0 +
0(
1'
#200000
0'
#210000
b1 4
02
b0 6
b1 0
0-
b0 /
b1 +
1'
#220000
0'
#230000
b1 .
b1 3
b10 +
1'
#240000
0'
#250000
b10 3
b10 .
b11 +
1'
#260000
0'
#270000
b11 .
b11 3
b100 +
1'
#280000
0'
#290000
b100 3
b100 .
b101 +
1'
#300000
0'
#310000
b101 .
b101 3
b110 +
1'
#320000
0'
#330000
b110 3
b110 .
b111 +
1'
#340000
0'
#350000
b111 .
b111 3
b1000 +
1'
#360000
0'
#370000
b1000 3
b1000 .
b1001 +
1'
#380000
0'
#390000
b1001 .
b1001 3
b1010 +
1'
#400000
0'
#410000
b1010 3
b1010 .
b1011 +
1'
#420000
0'
#430000
b1011 .
b1011 3
b1100 +
1'
#440000
0'
#450000
b1100 3
b1100 .
b1101 +
1'
#460000
0'
#470000
b1101 .
b1101 3
b1110 +
1'
#480000
0'
#490000
b1110 3
b1110 .
b1111 +
1'
#500000
0'
#510000
b1111 .
b1111 3
b10000 +
1'
#520000
0'
#530000
b10000 3
b10000 .
b10001 +
1'
#540000
0'
#550000
b10001 .
b10001 3
b10010 +
1'
#560000
0'
#570000
b10010 3
b10010 .
b10011 +
1'
#580000
0'
#590000
b10011 .
b10011 3
b10100 +
1'
#600000
0'
#610000
b10100 3
b10100 .
b10101 +
1'
#620000
0'
#630000
b10101 .
b10101 3
b10110 +
1'
#640000
0'
#650000
b10110 3
b10110 .
b10111 +
1'
#660000
0'
#670000
b10111 .
b10111 3
b11000 +
1'
#680000
0'
#690000
b11000 3
b11000 .
b11001 +
1'
#700000
0'
#710000
b11001 .
b11001 3
b11010 +
1'
#720000
0'
#730000
b11010 3
b11010 .
b11011 +
1'
#740000
0'
#750000
b11011 .
b11011 3
b11100 +
1'
#760000
0'
#770000
b11100 3
b11100 .
b11101 +
1'
#780000
0'
#790000
b11101 .
b11101 3
b11110 +
1'
#800000
0'
#810000
b11110 3
b11110 .
b11111 +
1'
#820000
0'
#830000
b11111 .
b11111 3
b100000 +
1'
#840000
0'
#850000
b100000 3
b100000 .
b100001 +
1'
#860000
0'
#870000
b100001 .
b100001 3
b100010 +
1'
#880000
0'
#890000
b100010 3
b100010 .
b100011 +
1'
#900000
0'
#910000
b100011 .
b100011 3
b100100 +
1'
#920000
0'
#930000
b100100 3
b100100 .
b100101 +
1'
#940000
0'
#950000
b100101 .
b100101 3
b100110 +
1'
#960000
0'
#970000
b100110 3
b100110 .
b100111 +
1'
#980000
0'
#990000
b100111 .
b100111 3
b101000 +
1'
#1000000
0'
#1010000
b101000 3
b101000 .
b101001 +
1'
#1020000
0'
#1030000
b101001 .
b101001 3
b101010 +
1'
#1040000
0'
#1050000
b101010 3
b101010 .
b101011 +
1'
#1060000
0'
#1070000
b101011 .
b101011 3
b101100 +
1'
#1080000
0'
#1090000
b101100 3
b101100 .
b101101 +
1'
#1100000
0'
#1110000
b101101 .
b101101 3
b101110 +
1'
#1120000
0'
#1130000
b101110 3
b101110 .
b101111 +
1'
#1140000
0'
#1150000
b101111 .
b101111 3
b110000 +
1'
#1160000
0'
#1170000
b110000 3
b110000 .
b110001 +
1'
#1180000
0'
#1190000
b110001 .
b110001 3
b110010 +
1'
#1200000
0'
#1210000
b110010 3
b110010 .
b110011 +
1'
#1220000
0'
#1230000
b110011 .
b110011 3
b110100 +
1'
#1240000
0'
#1250000
b110100 3
b110100 .
b110101 +
1'
#1260000
0'
#1270000
b110101 .
b110101 3
b110110 +
1'
#1280000
0'
#1290000
b110110 3
b110110 .
b110111 +
1'
#1300000
0'
#1310000
b110111 .
b110111 3
b111000 +
1'
#1320000
0'
#1330000
b111000 3
b111000 .
b111001 +
1'
#1340000
0'
#1350000
b111001 .
b111001 3
b111010 +
1'
#1360000
0'
#1370000
b111010 3
b111010 .
b111011 +
1'
#1380000
0'
#1390000
b111011 .
b111011 3
b111100 +
1'
#1400000
0'
#1410000
b111100 3
b111100 .
b111101 +
1'
#1420000
0'
#1430000
b111101 .
b111101 3
b111110 +
1'
#1440000
0'
#1450000
b111110 3
b111110 .
b111111 +
1'
#1460000
0'
#1470000
b111111 .
b111111 3
b1000000 +
1'
#1480000
0'
#1490000
b1000000 3
b1000000 .
b1000001 +
1'
#1500000
0'
#1510000
b1000001 .
b1000001 3
b1000010 +
1'
#1520000
0'
#1530000
b1000010 3
b1000010 .
b1000011 +
1'
#1540000
0'
#1550000
b1000011 .
b1000011 3
b1000100 +
1'
#1560000
0'
#1570000
b1000100 3
b1000100 .
b1000101 +
1'
#1580000
0'
#1590000
b1000101 .
b1000101 3
b1000110 +
1'
#1600000
0'
#1610000
b1000110 3
b1000110 .
b1000111 +
1'
#1620000
0'
#1630000
b1000111 .
b1000111 3
b1001000 +
1'
#1640000
0'
#1650000
b1001000 3
b1001000 .
b1001001 +
1'
#1660000
0'
#1670000
b1001001 .
b1001001 3
b1001010 +
1'
#1680000
0'
#1690000
b1001010 3
b1001010 .
b1001011 +
1'
#1700000
0'
#1710000
b1001011 .
b1001011 3
b1001100 +
1'
#1720000
0'
#1730000
b1001100 3
b1001100 .
b1001101 +
1'
#1740000
0'
#1750000
b1001101 .
b1001101 3
b1001110 +
1'
#1760000
0'
#1770000
b1001110 3
b1001110 .
b1001111 +
1'
#1780000
0'
#1790000
b1001111 .
b1001111 3
b1010000 +
1'
#1800000
0'
#1810000
b1010000 3
b1010000 .
b1010001 +
1'
#1820000
0'
#1830000
b1010001 .
b1010001 3
b1010010 +
1'
#1840000
0'
#1850000
b1010010 3
b1010010 .
b1010011 +
1'
#1860000
0'
#1870000
b1010011 .
b1010011 3
b1010100 +
1'
#1880000
0'
#1890000
b1010100 3
b1010100 .
b1010101 +
1'
#1900000
0'
#1910000
b1010101 .
b1010101 3
b1010110 +
1'
#1920000
0'
#1930000
b1010110 3
b1010110 .
b1010111 +
1'
#1940000
0'
#1950000
b1010111 .
b1010111 3
b1011000 +
1'
#1960000
0'
#1970000
b1011000 3
b1011000 .
b1011001 +
1'
#1980000
0'
#1990000
b1011001 .
b1011001 3
b1011010 +
1'
#2000000
0'
#2010000
b1011010 3
b1011010 .
b1011011 +
1'
#2020000
0'
#2030000
b1011011 .
b1011011 3
b1011100 +
1'
#2040000
0'
#2050000
b1011100 3
b1011100 .
b1011101 +
1'
#2060000
0'
#2070000
b1011101 .
b1011101 3
b1011110 +
1'
#2080000
0'
#2090000
b1011110 3
b1011110 .
b1011111 +
1'
#2100000
0'
#2110000
b1011111 .
b1011111 3
b1100000 +
1'
#2120000
0'
#2130000
b1100000 3
b1100000 .
b1100001 +
1'
#2140000
0'
#2150000
b1100001 .
b1100001 3
b1100010 +
1'
#2160000
0'
#2170000
b1100010 3
b1100010 .
b1100011 +
1'
#2180000
0'
#2190000
b10 5
b1100011 .
b1100011 3
b1100100 +
1'
#2200000
0'
#2210000
b0 3
1%
b10 4
b0 .
0"
1&
b10 0
b1100101 +
1'
#2220000
0'
#2230000
0&
0!
0%
b0 +
1'
#2240000
0'
#2250000
b11 5
11
b1 6
1,
b1 /
1(
b0 +
1'
#2260000
0'
#2270000
0,
b11 /
b11 0
01
b11 6
b11 4
b1 +
1'
#2280000
0'
#2290000
b1 3
b1 .
b10 +
1'
#2300000
0'
#2310000
b10 .
b10 3
b11 +
1'
#2320000
0'
#2330000
b11 3
b11 .
b100 +
1'
#2340000
0'
#2350000
b100 .
b100 3
b101 +
1'
#2360000
0'
#2370000
b101 3
b101 .
b110 +
1'
#2380000
0'
#2390000
b110 .
b110 3
b111 +
1'
#2400000
0'
#2410000
b111 3
b111 .
b1000 +
1'
#2420000
0'
#2430000
b1000 .
b1000 3
b1001 +
1'
#2440000
0'
#2450000
b1001 3
b1001 .
b1010 +
1'
#2460000
0'
#2470000
b1010 .
b1010 3
b1011 +
1'
#2480000
0'
#2490000
b1011 3
b1011 .
b1100 +
1'
#2500000
0'
#2510000
b1100 .
b1100 3
b1101 +
1'
#2520000
0'
#2530000
b1101 3
b1101 .
b1110 +
1'
#2540000
0'
#2550000
b1110 .
b1110 3
b1111 +
1'
#2560000
0'
#2570000
b1111 3
b1111 .
b10000 +
1'
#2580000
0'
#2590000
b10000 .
b10000 3
b10001 +
1'
#2600000
0'
#2610000
b10001 3
b10001 .
b10010 +
1'
#2620000
0'
#2630000
b10010 .
b10010 3
b10011 +
1'
#2640000
0'
#2650000
b10011 3
b10011 .
b10100 +
1'
#2660000
0'
#2670000
b10100 .
b10100 3
b10101 +
1'
#2680000
0'
#2690000
b10101 3
b10101 .
b10110 +
1'
#2700000
0'
#2710000
b10110 .
b10110 3
b10111 +
1'
#2720000
0'
#2730000
b10111 3
b10111 .
b11000 +
1'
#2740000
0'
#2750000
b11000 .
b11000 3
b11001 +
1'
#2760000
0'
#2770000
b11001 3
b11001 .
b11010 +
1'
#2780000
0'
#2790000
b11010 .
b11010 3
b11011 +
1'
#2800000
0'
#2810000
b11011 3
b11011 .
b11100 +
1'
#2820000
0'
#2830000
b11100 .
b11100 3
b11101 +
1'
#2840000
0'
#2850000
b11101 3
b11101 .
b11110 +
1'
#2860000
0'
#2870000
b11110 .
b11110 3
b11111 +
1'
#2880000
0'
#2890000
b11111 3
b11111 .
b100000 +
1'
#2900000
0'
#2910000
b100000 .
b100000 3
b100001 +
1'
#2920000
0'
#2930000
b100001 3
b100001 .
b100010 +
1'
#2940000
0'
#2950000
b100010 .
b100010 3
b100011 +
1'
#2960000
0'
#2970000
b100011 3
b100011 .
b100100 +
1'
#2980000
0'
#2990000
b100100 .
b100100 3
b100101 +
1'
#3000000
0'
#3010000
b100101 3
b100101 .
b100110 +
1'
#3020000
0'
#3030000
b100110 .
b100110 3
b100111 +
1'
#3040000
0'
#3050000
b100111 3
b100111 .
b101000 +
1'
#3060000
0'
#3070000
b101000 .
b101000 3
b101001 +
1'
#3080000
0'
#3090000
b101001 3
b101001 .
b101010 +
1'
#3100000
0'
#3110000
b101010 .
b101010 3
b101011 +
1'
#3120000
0'
#3130000
b101011 3
b101011 .
b101100 +
1'
#3140000
0'
#3150000
b101100 .
b101100 3
b101101 +
1'
#3160000
0'
#3170000
b101101 3
b101101 .
b101110 +
1'
#3180000
0'
#3190000
b101110 .
b101110 3
b101111 +
1'
#3200000
0'
#3210000
b101111 3
b101111 .
b110000 +
1'
#3220000
0'
#3230000
b110000 .
b110000 3
b110001 +
1'
#3240000
0'
#3250000
b110001 3
b110001 .
b110010 +
1'
#3260000
0'
#3270000
b110010 .
b110010 3
b110011 +
1'
#3280000
0'
#3290000
b110011 3
b110011 .
b110100 +
1'
#3300000
0'
#3310000
b110100 .
b110100 3
b110101 +
1'
#3320000
0'
#3330000
b110101 3
b110101 .
b110110 +
1'
#3340000
0'
#3350000
b110110 .
b110110 3
b110111 +
1'
#3360000
0'
#3370000
b110111 3
b110111 .
b111000 +
1'
#3380000
0'
#3390000
b111000 .
b111000 3
b111001 +
1'
#3400000
0'
#3410000
b111001 3
b111001 .
b111010 +
1'
#3420000
0'
#3430000
b111010 .
b111010 3
b111011 +
1'
#3440000
0'
#3450000
b111011 3
b111011 .
b111100 +
1'
#3460000
0'
#3470000
b111100 .
b111100 3
b111101 +
1'
#3480000
0'
#3490000
b111101 3
b111101 .
b111110 +
1'
#3500000
0'
#3510000
b111110 .
b111110 3
b111111 +
1'
#3520000
0'
#3530000
b111111 3
b111111 .
b1000000 +
1'
#3540000
0'
#3550000
b1000000 .
b1000000 3
b1000001 +
1'
#3560000
0'
#3570000
b1000001 3
b1000001 .
b1000010 +
1'
#3580000
0'
#3590000
b1000010 .
b1000010 3
b1000011 +
1'
#3600000
0'
#3610000
b1000011 3
b1000011 .
b1000100 +
1'
#3620000
0'
#3630000
b1000100 .
b1000100 3
b1000101 +
1'
#3640000
0'
#3650000
b1000101 3
b1000101 .
b1000110 +
1'
#3660000
0'
#3670000
b1000110 .
b1000110 3
b1000111 +
1'
#3680000
0'
#3690000
b1000111 3
b1000111 .
b1001000 +
1'
#3700000
0'
#3710000
b1001000 .
b1001000 3
b1001001 +
1'
#3720000
0'
#3730000
b1001001 3
b1001001 .
b1001010 +
1'
#3740000
0'
#3750000
b1001010 .
b1001010 3
b1001011 +
1'
#3760000
0'
#3770000
b1001011 3
b1001011 .
b1001100 +
1'
#3780000
0'
#3790000
b1001100 .
b1001100 3
b1001101 +
1'
#3800000
0'
#3810000
b1001101 3
b1001101 .
b1001110 +
1'
#3820000
0'
#3830000
b1001110 .
b1001110 3
b1001111 +
1'
#3840000
0'
#3850000
b1001111 3
b1001111 .
b1010000 +
1'
#3860000
0'
#3870000
b1010000 .
b1010000 3
b1010001 +
1'
#3880000
0'
#3890000
b1010001 3
b1010001 .
b1010010 +
1'
#3900000
0'
#3910000
b1010010 .
b1010010 3
b1010011 +
1'
#3920000
0'
#3930000
b1010011 3
b1010011 .
b1010100 +
1'
#3940000
0'
#3950000
b1010100 .
b1010100 3
b1010101 +
1'
#3960000
0'
#3970000
b1010101 3
b1010101 .
b1010110 +
1'
#3980000
0'
#3990000
b1010110 .
b1010110 3
b1010111 +
1'
#4000000
0'
#4010000
b1010111 3
b1010111 .
b1011000 +
1'
#4020000
0'
#4030000
b1011000 .
b1011000 3
b1011001 +
1'
#4040000
0'
#4050000
b1011001 3
b1011001 .
b1011010 +
1'
#4060000
0'
#4070000
b1011010 .
b1011010 3
b1011011 +
1'
#4080000
0'
#4090000
b1011011 3
b1011011 .
b1011100 +
1'
#4100000
0'
#4110000
b1011100 .
b1011100 3
b1011101 +
1'
#4120000
0'
#4130000
b1011101 3
b1011101 .
b1011110 +
1'
#4140000
0'
#4150000
b1011110 .
b1011110 3
b1011111 +
1'
#4160000
0'
#4170000
b1011111 3
b1011111 .
b1100000 +
1'
#4180000
0'
#4190000
b1100000 .
b1100000 3
b1100001 +
1'
#4200000
0'
#4210000
b1100001 3
b1100001 .
b1100010 +
1'
#4220000
0'
#4230000
b1100010 .
b1100010 3
b1100011 +
1'
#4240000
0'
#4250000
b0 5
b1100011 3
b1100011 .
b1100100 +
1'
#4260000
0'
#4270000
1"
b0 .
1$
b0 0
b0 4
b0 3
1#
b1100101 +
1'
#4280000
0'
#4290000
1!
0#
0$
b0 +
1'
#4300000
0'
#4310000
b1 5
1-
b10 /
12
b10 6
0(
b1 +
1'
#4320000
0'
#4330000
b1 4
02
b0 6
b1 0
0-
b0 /
1'
#4340000
0'
#4350000
b1 .
b1 3
1'
#4360000
0'
#4370000
b10 3
b10 .
1'
#4380000
0'
#4390000
b11 .
b11 3
1'
#4400000
0'
#4410000
b100 3
b100 .
1'
#4420000
0'
#4430000
b101 .
b101 3
1'
#4440000
0'
#4450000
b110 3
b110 .
1'
#4460000
0'
#4470000
b111 .
b111 3
1'
#4480000
0'
#4490000
b1000 3
b1000 .
1'
#4500000
0'
#4510000
b1001 .
b1001 3
1'
#4520000
0'
#4530000
b1010 3
b1010 .
1'
#4540000
0'
#4550000
b1011 .
b1011 3
1'
#4560000
0'
#4570000
b1100 3
b1100 .
1'
#4580000
0'
#4590000
b1101 .
b1101 3
1'
#4600000
0'
#4610000
b1110 3
b1110 .
1'
#4620000
0'
#4630000
b1111 .
b1111 3
1'
#4640000
0'
#4650000
b10000 3
b10000 .
1'
#4660000
0'
#4670000
b10001 .
b10001 3
1'
#4680000
0'
#4690000
b10010 3
b10010 .
1'
#4700000
0'
#4710000
b10011 .
b10011 3
1'
#4720000
0'
#4730000
b10100 3
b10100 .
1'
#4740000
0'
#4750000
b10101 .
b10101 3
1'
#4760000
0'
#4770000
b10110 3
b10110 .
1'
#4780000
0'
#4790000
b10111 .
b10111 3
1'
#4800000
0'
#4810000
b11000 3
b11000 .
1'
#4820000
0'
#4830000
b11001 .
b11001 3
1'
#4840000
0'
#4850000
b11010 3
b11010 .
1'
#4860000
0'
#4870000
b11011 .
b11011 3
1'
#4880000
0'
