09. gray_converter/gray_converter.v
module gray_converter#
    (
        parameter N = 4
    )(
        input wire [N-1:0] bin_in,
        input wire [N-1:0] gray_in,
        output wire [N-1:0] gray_out,
        output wire [N-1:0] bin_out
    );
    assign gray_out = bin_in ^ (bin_in >> 1);
    genvar i;
    generate
        for (i = 0; i < N; i = i + 1) begin
            if (i == N - 1)
                assign bin_out[i] = gray_in[i];
            else
                assign bin_out[i] = gray_in[i] ^ bin_out[i + 1];
        end
    endgenerate
endmodule

09. gray_converter/tb_gray_converter.v

module gray_converter_tb;

    localparam  N = 4;

    reg [N-1:0] bin_in;
    reg [N-1:0] gray_in;
    wire [N-1:0] gray_out;
    wire [N-1:0] bin_out;

    gray_converter # (
                       .N(N)
                   )
                   gray_converter_inst (
                       .bin_in(bin_in),
                       .gray_in(gray_in),
                       .gray_out(gray_out),
                       .bin_out(bin_out)
                   );

    //always #5  clk = ! clk ;
    initial begin
        bin_in = 0;
        gray_in=0;
        #10;
        bin_in=4'b0000;
        gray_in=4'b0000;
        #10;
        bin_in=4'b0001;
        gray_in=4'b0001;
        #10;
        bin_in=4'b0010;
        gray_in=4'b0011;
        #10;
        bin_in=4'b0011;
        gray_in=4'b0010;
        #10;
        bin_in=4'b0100;
        gray_in=4'b0110;
        #10;
        bin_in=4'b0101;
        gray_in=4'b0111;
        #10;
        bin_in=4'b0110;
        gray_in=4'b0101;
        #10;
        bin_in=4'b0111;
        gray_in=4'b0100;
        #10;
        bin_in=4'b1000;
        gray_in=4'b1100;
        #10;
        bin_in=4'b1001;
        gray_in=4'b1101;
        #10;
        bin_in=4'b1010;
        gray_in=4'b1111;
        #10;
        bin_in=4'b1011;
        gray_in=4'b1110;
        #10;
        bin_in=4'b1100;
        gray_in=4'b1010;
        #10;
        bin_in=4'b1101;
        gray_in=4'b1011;
        #10;
        bin_in=4'b1110;
        gray_in=4'b1001;
        #10;
        bin_in=4'b1111;
        gray_in=4'b1000;
        #10;
        $finish;
    end
endmodule

09. gray_converter/tb_gray_converter.vcd
$date
	Wed Feb 18 21:27:33 2026
$end
$version
	Icarus Verilog
$end
$timescale
	1s
$end
$scope module gray_converter_tb $end
$var wire 4 ! gray_out [3:0] $end
$var wire 4 " bin_out [3:0] $end
$var reg 4 # bin_in [3:0] $end
$var reg 4 $ gray_in [3:0] $end
$scope module gray_converter_inst $end
$var wire 4 % bin_in [3:0] $end
$var wire 4 & gray_in [3:0] $end
$var wire 4 ' gray_out [3:0] $end
$var wire 4 ( bin_out [3:0] $end
$scope begin genblk1[0] $end
$scope begin genblk3 $end
$upscope $end
$upscope $end
$scope begin genblk1[1] $end
$scope begin genblk3 $end
$upscope $end
$upscope $end
$scope begin genblk1[2] $end
$scope begin genblk3 $end
$upscope $end
$upscope $end
$scope begin genblk1[3] $end
$scope begin genblk2 $end
$upscope $end
$upscope $end
$upscope $end
$upscope $end
$enddefinitions $end
#0
$dumpvars
b0 (
b0 '
b0 &
b0 %
b0 $
b0 #
b0 "
b0 !
$end
#20
b1 "
b1 (
b1 !
b1 '
b1 $
b1 &
b1 #
b1 %
#30
b10 "
b10 (
b11 !
b11 '
b11 $
b11 &
b10 #
b10 %
#40
b11 "
b11 (
b10 !
b10 '
b10 $
b10 &
b11 #
b11 %
#50
b100 "
b100 (
b110 !
b110 '
b110 $
b110 &
b100 #
b100 %
#60
b101 "
b101 (
b111 !
b111 '
b111 $
b111 &
b101 #
b101 %
#70
b110 "
b110 (
b101 !
b101 '
b101 $
b101 &
b110 #
b110 %
#80
b111 "
b111 (
b100 !
b100 '
b100 $
b100 &
b111 #
b111 %
#90
b1000 "
b1000 (
b1100 !
b1100 '
b1100 $
b1100 &
b1000 #
b1000 %
#100
b1001 "
b1001 (
b1101 !
b1101 '
b1101 $
b1101 &
b1001 #
b1001 %
#110
b1010 "
b1010 (
b1111 !
b1111 '
b1111 $
b1111 &
b1010 #
b1010 %
#120
b1011 "
b1011 (
b1110 !
b1110 '
b1110 $
b1110 &
b1011 #
b1011 %
#130
b1100 "
b1100 (
b1010 !
b1010 '
b1010 $
b1010 &
b1100 #
b1100 %
#140
b1101 "
b1101 (
b1011 !
b1011 '
b1011 $
b1011 &
b1101 #
b1101 %
#150
b1110 "
b1110 (
b1001 !
b1001 '
b1001 $
b1001 &
b1110 #
b1110 %
#160
b1111 "
b1111 (
b1000 !
b1000 '
b1000 $
b1000 &
b1111 #
b1111 %
