3.led_twinkle.v
module led_twinkle(
   Clk,
   Reset_n,
   Led
    );
    
   input Clk;
   input Reset_n;
   output reg Led;
   
   reg[24:0]counter;
   
   always@(posedge Clk or negedge Reset_n)
   if(!Reset_n)
      counter<=0;
   else if(counter==25_000_000-1)
       counter<=0;
   else 
       counter<=counter+1'd1;    
       
   always@(posedge Clk or negedge Reset_n)
   if(!Reset_n)
      Led<=1'b0;
   else if(counter==25_000_000-1)
      Led<=!Led;
   
endmodule

03. led_twinkle/led_twinkle_tb.v
`timescale 1ns / 1ns
// 仿真说明: led_twinkle 原计数上限 25_000_000（对应50MHz时钟1秒闪烁）。
//           仿真时创建一个参数缩小版模块 led_twinkle_sim，计数上限改为 10，
//           验证计数器翻转逻辑正确性。

// ── 仿真用缩参数模块（内嵌在 tb 中，不修改原文件）────────────────────
module led_twinkle_sim(
  input  Clk,
  input  Reset_n,
  output reg Led
);
  reg [4:0] counter;  // 只需5位
  localparam CNT_MAX = 10;  // 缩小到10，仿真快速完成

  always @(posedge Clk or negedge Reset_n)
    if (!Reset_n) counter <= 0;
    else if (counter == CNT_MAX - 1) counter <= 0;
    else counter <= counter + 1'd1;

  always @(posedge Clk or negedge Reset_n)
    if (!Reset_n) Led <= 1'b0;
    else if (counter == CNT_MAX - 1) Led <= !Led;
endmodule

// ── Testbench ────────────────────────────────────────────────────────
module led_twinkle_tb();

  reg  Clk, Reset_n;
  wire Led;
  wire Led_orig;  // 原模块输出（仅编译验证，不等其翻转）

  // 实例化仿真加速版
  led_twinkle_sim dut_sim(
    .Clk    (Clk),
    .Reset_n(Reset_n),
    .Led    (Led)
  );

  // 实例化原始模块（验证编译通过即可，不做功能断言）
  led_twinkle dut_orig(
    .Clk    (Clk),
    .Reset_n(Reset_n),
    .Led    (Led_orig)
  );

  initial Clk = 0;
  always #10 Clk = ~Clk;

  integer toggle_cnt;
  reg prev_Led;
  integer err;

  initial begin
    $dumpfile("led_twinkle_tb.vcd");
    $dumpvars(0, led_twinkle_tb);

    Reset_n  = 0;
    prev_Led = 0;
    toggle_cnt = 0;
    err = 0;

    #50; Reset_n = 1;

    // 等待 Led 翻转 6 次（3个完整周期，每周期 10*20ns=200ns）
    @(posedge Led); toggle_cnt = toggle_cnt + 1;
    @(negedge Led); toggle_cnt = toggle_cnt + 1;
    @(posedge Led); toggle_cnt = toggle_cnt + 1;
    @(negedge Led); toggle_cnt = toggle_cnt + 1;
    @(posedge Led); toggle_cnt = toggle_cnt + 1;
    @(negedge Led); toggle_cnt = toggle_cnt + 1;

    #50;
    if (toggle_cnt == 6)
      $display("[PASS] led_twinkle 计数器翻转正常，共翻转 %0d 次", toggle_cnt);
    else begin
      $display("[FAIL] led_twinkle 翻转次数异常：%0d", toggle_cnt);
      err = err + 1;
    end

    $finish;
  end

  // 超时保护
  initial begin
    #100000;
    $display("[TIMEOUT] led_twinkle 仿真超时");
    $finish;
  end
endmodule

03. led_twinkle/led_twinkle_tb.vcd
$date
	Wed Feb 18 21:26:33 2026
$end
$version
	Icarus Verilog
$end
$timescale
	1ns
$end
$scope module led_twinkle_tb $end
$var wire 1 ! Led_orig $end
$var wire 1 " Led $end
$var reg 1 # Clk $end
$var reg 1 $ Reset_n $end
$var reg 1 % prev_Led $end
$var integer 32 & err [31:0] $end
$var integer 32 ' toggle_cnt [31:0] $end
$scope module dut_orig $end
$var wire 1 # Clk $end
$var wire 1 $ Reset_n $end
$var reg 1 ! Led $end
$var reg 25 ( counter [24:0] $end
$upscope $end
$scope module dut_sim $end
$var wire 1 # Clk $end
$var wire 1 $ Reset_n $end
$var reg 1 " Led $end
$var reg 5 ) counter [4:0] $end
$upscope $end
$upscope $end
$enddefinitions $end
#0
$dumpvars
b0 )
b0 (
b0 '
b0 &
0%
0$
0#
0"
0!
$end
#10
1#
#20
0#
#30
1#
#40
0#
#50
b1 (
b1 )
1#
1$
#60
0#
#70
b10 )
b10 (
1#
#80
0#
#90
b11 (
b11 )
1#
#100
0#
#110
b100 )
b100 (
1#
#120
0#
#130
b101 (
b101 )
1#
#140
0#
#150
b110 )
b110 (
1#
#160
0#
#170
b111 (
b111 )
1#
#180
0#
#190
b1000 )
b1000 (
1#
#200
0#
#210
b1001 (
b1001 )
1#
#220
0#
#230
b1 '
b0 )
1"
b1010 (
1#
#240
0#
#250
b1011 (
b1 )
1#
#260
0#
#270
b10 )
b1100 (
1#
#280
0#
#290
b1101 (
b11 )
1#
#300
0#
#310
b100 )
b1110 (
1#
#320
0#
#330
b1111 (
b101 )
1#
#340
0#
#350
b110 )
b10000 (
1#
#360
0#
#370
b10001 (
b111 )
1#
#380
0#
#390
b1000 )
b10010 (
1#
#400
0#
#410
b10011 (
b1001 )
1#
#420
0#
#430
b10 '
b0 )
0"
b10100 (
1#
#440
0#
#450
b10101 (
b1 )
1#
#460
0#
#470
b10 )
b10110 (
1#
#480
0#
#490
b10111 (
b11 )
1#
#500
0#
#510
b100 )
b11000 (
1#
#520
0#
#530
b11001 (
b101 )
1#
#540
0#
#550
b110 )
b11010 (
1#
#560
0#
#570
b11011 (
b111 )
1#
#580
0#
#590
b1000 )
b11100 (
1#
#600
0#
#610
b11101 (
b1001 )
1#
#620
0#
#630
b11 '
b0 )
1"
b11110 (
1#
#640
0#
#650
b11111 (
b1 )
1#
#660
0#
#670
b10 )
b100000 (
1#
#680
0#
#690
b100001 (
b11 )
1#
#700
0#
#710
b100 )
b100010 (
1#
#720
0#
#730
b100011 (
b101 )
1#
#740
0#
#750
b110 )
b100100 (
1#
#760
0#
#770
b100101 (
b111 )
1#
#780
0#
#790
b1000 )
b100110 (
1#
#800
0#
#810
b100111 (
b1001 )
1#
#820
0#
#830
b100 '
b0 )
0"
b101000 (
1#
#840
0#
#850
b101001 (
b1 )
1#
#860
0#
#870
b10 )
b101010 (
1#
#880
0#
#890
b101011 (
b11 )
1#
#900
0#
#910
b100 )
b101100 (
1#
#920
0#
#930
b101101 (
b101 )
1#
#940
0#
#950
b110 )
b101110 (
1#
#960
0#
#970
b101111 (
b111 )
1#
#980
0#
#990
b1000 )
b110000 (
1#
#1000
0#
#1010
b110001 (
b1001 )
1#
#1020
0#
#1030
b101 '
b0 )
1"
b110010 (
1#
#1040
0#
#1050
b110011 (
b1 )
1#
#1060
0#
#1070
b10 )
b110100 (
1#
#1080
0#
#1090
b110101 (
b11 )
1#
#1100
0#
#1110
b100 )
b110110 (
1#
#1120
0#
#1130
b110111 (
b101 )
1#
#1140
0#
#1150
b110 )
b111000 (
1#
#1160
0#
#1170
b111001 (
b111 )
1#
#1180
0#
#1190
b1000 )
b111010 (
1#
#1200
0#
#1210
b111011 (
b1001 )
1#
#1220
0#
#1230
b110 '
b0 )
0"
b111100 (
1#
#1240
0#
#1250
b111101 (
b1 )
1#
#1260
0#
#1270
b10 )
b111110 (
1#
